{"page": 182, "surahs": [{"num": 8, "ar": "الأنفال", "en": "Al-Anfāl"}], "juz": 10, "quran": null, "quran_com": "https://quran.com/page/182", "t1": {"episode": "T1-e50", "date": "2021-10-08", "session_number": 50, "youtube_id": "ipZ08RYcdsc", "start_s": 3206, "end_s": 3557, "start": "53:26", "end": "59:17", "presenter": "شريف كف الغزال", "unnamed": false, "voice_code": "Coral Owl", "confidence": "high", "text": "الله يزيد الخير بارك الله فيك أخي أخونا عبد الرحمن اليوم أصل تأصيلات ما شاء الله الله يزيد الخير لثورات الربيع العربي الله يزيد الخير أخي بسم الله الرحمن الرحيم والصلاة والسلام على سيدنا محمد الخاتم الأملياء ابن السنين الصفحة الأخيرة والصفحة 182 السلام عليكم شباب الله يخليكم بارك الله فيكم الصفحة تبدأ بالحديث عن موضوع الغنائم وكيف اقتسامها والآية تذكر وعلم أنما غنيمتم من شيئا فأنا لله خمسه وللرسول خمسه وللرسول خمسه وللرسول وللقربة واليتامة والمساكني وابن السبيل إن كنتم آمنتم بالله وما أنزلنا على عبدنا سبحان الله بداية السورة تؤكد الآيات أن ملكية الأنفال قد تم البت فيها يسألونك عن الأنفال قل الأنفال لله والرسول فاتقوا الله إلى تتمة الآية الله سبحانه وتعالى نزع ملكية الغنائم في المعركة وردها إلى الله ورسوله في بداية السورة ليخلص الأمر كله لله والرسول وليتجرد المؤمنون من كل ملابسات الأرض فالمعركة لله وفي سبيل الله طاعة لله يحكمونه بأموالهم وأرواحهم ويحكمونه في أمرهم كله ولكن بعد أن استقر الإيمان واستسلموا لله سبحانه وتعالى وارتضوا حكمه عاد ليرد عليهم أربع خماس الغنيمة فالمنهج القرآني فعلا هو يعني يواجه الواقع الفعلي بأحكام منظمة هناك غنائم هناك محاربون هؤلاء المحاربون يجاهدون بالمال والنفس يتطوعون للجهاد يجهزون أنفسهم على نفقتهم الخاصة فهذه يعني حاجة واقعية الحقيقة لا تناقض برد ملكية الغنائم ابتداء لله ورسوله طبعا لا ندخل في الروايات والأراء الفقهية التي اختلف بعضها حول الفرق بين الأنفال والغنائم والكلمة الحقيقة بالتوصيف الفقهي ومدلول الخمس كيفية تقسيمه هل الخمس لله هو نفسه للرسول أم هل هو مستقل هل الخمس الخمس الذي للرسول صلى الله عليه وسلم خاص به أم ينتقل لكل إمام للمسلمين بعده طبعا نحن في هذا العصر لا يوجد قضية غنائم لأنه ليس هناك قضية جهاد للأسف بالمعنى المذكور في الآيات ربما من الحكم أن لا ندخل بالقضايا الفقهية حتى يحين وقتها إن شاء الله وينشأ المجتمع الإسلامي ويواجه حالة جهاد فعلي بوقته النقطة الأخرى الحقيقة هي البيانة الإلهية عندما يذكر إن كنتم آمنتم بالله وما أنزلنا على عبدنا يوم الفرقان يوم التقد جمعان يعني على عبدنا سبحان الله العبودية لله هي حقيقة الإيمان أخوتي يعني هي أعلى مقام هي أكرم مقام للإنسان يبلغ إليه بتكريم من الله سبحانه وتعالى وتكرر هذا الوصف طبعا عدة مرات سبحان الذي أسرى بعبده ليلا الحمد لله الذي أنزل على عبده الكتاب وإن كنتم في رب مما نزلنا على عبدنا يعني عدة آيات جعلت مقام العبودية من أرقى المقامات النقطة الأخرى لتدبرية الحقيقة موضوع وصف يوم بدر بيوم الفرقان فرقان يعني فرقان بين الحق والباطل فرقان بين عهد الصبر والمصابرة والتجمع والانتظار قبل بدر وعهد القوة والمبادئة والاندفاع بعد بدر فرقان بين عهدين في تاريخ البشرية حتى قبل قيام النظام الإسلامي والعهد بعد الانتصار والتمكين فرقان بين تصورين لعوامل النصر وعوامل الهزيمة الحقيقية وليس العوامل الظاهرية وكانت بدر فرقانا بين الحق والباطل بمدلول آخر أيضا يعني الحق لا يثبت والباطل لا ينهار بمجرد البيان النظري مثل الأخونا يعني عبد الرحمن الحية يعني لا يمكن أن ينهار بمجرد البيان النظري أو الحديث النظري عن الحق والباطل بل لابد من أن يتحطم سلطان الباطل ويعلو سلطان الحق فالإسلام منهج حركي واقعي معاش لا مجرد نظرية أو نظرية للمعرفة أو الجدل أو المنطق الحي يعني لابد من فعل نقطة أخرى كان من تدبير الله سبحانه وتعالى في المعركة أن يرى رسول الله صلى الله عليه وسلم الكافرين في الرؤية بمنامه يراهم قليلا لا قوة لهم ولا وزن فينبئ الصحابة برؤياه فيستبشروا ويتشجعوا على خوض المعركة بثقة فهم الذين خرجوا على غير استعداد وعلى غير توقع للقتال حتى وحينما التقت جمعان وجها لوجه تكررت الرؤية النبوية الصادقة وكانت تدبير الله ما أغرى الفريقين بخوض المعركة واللفتة هنا أن المؤمنون يرون أعداهم قليلا يعني يرونهم بعين الحقيقة بوجود الدعم الله سبحانه وتعالى والملائكة حولهم وأيضا المشركون يرون المؤمنين قليلا بعين الظاهر يعني ثلاث أضعاف أو أكثر ومن رأي ذلك تحققت غاية التدبير الإلهي ووقع الأمر الذي أراد الله سبحانه وتعالى وإلى الله ترجع الأمور وفي نهاية طبعا هناك إحاءات قواعد وقواعد وتوجيهات سريعة يعني حول ضرورة السبات عند لقاء العدو والاتصال لله سبحانه وتعالى من خلال الذكر والطاعة لله ورسوله وتجنب النزاع والشقاق والصبر على تقاليف المعركة والحذر من البطر والرياء وربما يتم نقاشها إن شاء الله الإسبوع القادم خلال نقاش الصفحة القادمة إذا أحيانا الله جزاكم الله خير", "tad": {"ayah_range": "8:41-8:45", "presenter": "شريف كف الغزال", "time_range": {"start": "53:26", "end": "59:17"}, "confidence": 0.99, "assignment": "match", "has_tadabbur": true, "tadabbur": "تبدأ الصفحة بالحديث عن الغنائم وكيفية اقتسامها [8:41]. وبداية السورة كانت قد أكدت أن ملكية الأنفال قد حُسمت: الأنفال لله والرسول. الله سبحانه وتعالى نزع ملكية الغنائم في المعركة وردها إلى الله ورسوله، ليخلص الأمر كله لله وللرسول، وليتجرد المؤمنون من كل ملابسات الأرض؛ فالمعركة لله، وفي سبيل الله، وطاعة لله، يخوضونها بأموالهم وأرواحهم، ويحكّمون الله ورسوله في أمرهم كله. لكن بعد أن استقر الإيمان، واستسلموا لله سبحانه وتعالى، وارتضوا حكمه، عاد فرد عليهم أربعة أخماس الغنيمة.\nالمنهج القرآني يواجه الواقع الفعلي بأحكام منظمة. هناك غنائم، وهناك محاربون يجاهدون بالمال والنفس، ويتطوعون للجهاد، ويجهزون أنفسهم على نفقتهم الخاصة. فهذه حاجة واقعية لا تناقض رد ملكية الغنائم ابتداءً لله ورسوله. ولا أريد الدخول هنا في الروايات والآراء الفقهية التي اختلفت حول الفرق بين الأنفال والغنائم، ولا في مدلول الخمس وكيفية تقسيمه: هل الخمس لله هو نفسه للرسول أم هو مستقل؟ وهل الخمس الذي للرسول ﷺ خاص به أم ينتقل لكل إمام للمسلمين بعده؟ في هذا العصر لا توجد قضية غنائم؛ لأنه لا توجد قضية جهاد بالمعنى المذكور في الآيات، ولعل من الحكمة ألا ندخل في هذه القضايا الفقهية حتى يحين وقتها، وينشأ المجتمع الإسلامي، ويواجه حالة جهاد فعلي.\nثم ألتفت إلى البيان الإلهي في قوله: إن كنتم آمنتم بالله وما أنزل على عبده يوم الفرقان [8:41]. وصف «عبدنا» عظيم؛ فالعبودية لله هي حقيقة الإيمان، وهي أعلى مقام وأكرم مقام يبلغه الإنسان بتكريم من الله سبحانه وتعالى. وتكرر هذا الوصف في مواضع كثيرة، كقوله عن الإسراء بعبده [17:1]، وقوله عن إنزال الكتاب على عبده [18:1]، وقوله في التحدي بما نزل على عبده [2:23].\nومن اللطائف التدبرية وصف يوم بدر بيوم الفرقان. بدر فرقان بين الحق والباطل، وفرقان بين عهد الصبر والمصابرة والتجمع والانتظار قبل بدر، وعهد القوة والمبادأة والاندفاع بعد بدر. وهو فرقان بين عهدين في تاريخ البشرية: العهد قبل قيام النظام الإسلامي، والعهد بعد الانتصار والتمكين. وهو فرقان أيضًا بين تصورين لعوامل النصر وعوامل الهزيمة الحقيقية، لا العوامل الظاهرية فقط. وكانت بدر فرقانًا بمدلول آخر: فالحق لا يثبت، والباطل لا ينهار، بمجرد البيان النظري أو الحديث النظري عن الحق والباطل؛ بل لا بد أن يتحطم سلطان الباطل، وأن يعلو سلطان الحق. الإسلام منهج حركي واقعي معاش، لا مجرد نظرية للمعرفة أو الجدل أو المنطق. لا بد من فعل.\nثم أرى من تدبير الله سبحانه وتعالى في المعركة أنه أرى رسول الله ﷺ الكافرين في الرؤيا قليلين، لا قوة لهم ولا وزن [8:43]، فأنبأ الصحابة برؤياه، فاستبشروا وتشجعوا على خوض المعركة بثقة، وهم الذين خرجوا على غير استعداد وعلى غير توقع للقتال. وحين التقى الجمعان وجهًا لوجه تكررت الرؤية النبوية الصادقة، وكانت من تدبير الله ما أغرى الفريقين بخوض المعركة [8:44]. واللفتة هنا أن المؤمنين يرون أعداءهم قليلين بعين الحقيقة، بوجود دعم الله سبحانه وتعالى والملائكة حولهم. والمشركون يرون المؤمنين قليلين بعين الظاهر؛ فالفارق العددي كان نحو ثلاثة أضعاف أو أكثر. ومن وراء ذلك تحققت غاية التدبير الإلهي، ووقع الأمر الذي أراد الله سبحانه وتعالى، وإلى الله ترجع الأمور.\nوفي نهاية الصفحة وما يليها إيحاءات وقواعد وتوجيهات سريعة: ضرورة الثبات عند لقاء العدو [8:45]، والاتصال بالله سبحانه وتعالى من خلال الذكر، وطاعة الله ورسوله، وتجنب النزاع والشقاق، والصبر على تكاليف المعركة، والحذر من البطر والرياء. وربما يتم نقاش بعضها في الأسبوع القادم عند الصفحة التالية إن أحيانا الله.", "key_message": "يريد ربي مني أن أتجرد لله في المال والنصر، وأن أرى يوم الفرقان بتدبيره لا بمجرد الأسباب، وأن أثبت عند المواجهة مع كثرة الذكر.", "lessons": ["أرد ملكية ما أكسبه في سبيل الله إلى الله ورسوله قبل أن أنظر إلى حقي ونصيبي.", "أفهم أن الأحكام القرآنية تعالج واقعًا فعليًا منظمًا، لا مجرد معان نظرية.", "أعتز بمقام العبودية لله؛ فهو أكرم مقام للإنسان.", "أدرك أن الحق يحتاج فعلًا وسلطانًا يرفع الباطل، لا بيانًا نظريًا فقط.", "أثبت عند اللقاء، وأتصل بالله بالذكر، وأحذر النزاع والرياء والبطر."], "themes": ["أحكام الغنائم وتجريد الملك", "يوم الفرقان", "تدبير الله للنصر", "الثبات والذكر"], "keywords": ["الغنائم", "الخمس", "الأنفال", "العبودية", "يوم الفرقان", "بدر", "الرؤيا", "التدبير الإلهي", "الثبات", "الذكر"], "quran_quotes": [{"surah": 8, "ayah": 41, "ayah_end": null, "snippet": "واعلموا أنما غنمتم", "ayah_text": "۞ وَاعْلَمُوا أَنَّمَا غَنِمْتُمْ مِنْ شَيْءٍ فَأَنَّ لِلَّهِ خُمُسَهُ وَلِلرَّسُولِ وَلِذِي الْقُرْبَىٰ وَالْيَتَامَىٰ وَالْمَسَاكِينِ وَابْنِ السَّبِيلِ إِنْ كُنْتُمْ آمَنْتُمْ بِاللَّهِ وَمَا أَنْزَلْنَا عَلَىٰ عَبْدِنَا يَوْمَ الْفُرْقَانِ يَوْمَ الْتَقَى الْجَمْعَانِ ۗ وَاللَّهُ عَلَىٰ كُلِّ شَيْءٍ قَدِيرٌ"}, {"surah": 8, "ayah": 41, "ayah_end": null, "snippet": "فأن لله خمسه وللرسول", "ayah_text": "۞ وَاعْلَمُوا أَنَّمَا غَنِمْتُمْ مِنْ شَيْءٍ فَأَنَّ لِلَّهِ خُمُسَهُ وَلِلرَّسُولِ وَلِذِي الْقُرْبَىٰ وَالْيَتَامَىٰ وَالْمَسَاكِينِ وَابْنِ السَّبِيلِ إِنْ كُنْتُمْ آمَنْتُمْ بِاللَّهِ وَمَا أَنْزَلْنَا عَلَىٰ عَبْدِنَا يَوْمَ الْفُرْقَانِ يَوْمَ الْتَقَى الْجَمْعَانِ ۗ وَاللَّهُ عَلَىٰ كُلِّ شَيْءٍ قَدِيرٌ"}, {"surah": 8, "ayah": 41, "ayah_end": null, "snippet": "ما أنزلنا على عبدنا", "ayah_text": "۞ وَاعْلَمُوا أَنَّمَا غَنِمْتُمْ مِنْ شَيْءٍ فَأَنَّ لِلَّهِ خُمُسَهُ وَلِلرَّسُولِ وَلِذِي الْقُرْبَىٰ وَالْيَتَامَىٰ وَالْمَسَاكِينِ وَابْنِ السَّبِيلِ إِنْ كُنْتُمْ آمَنْتُمْ بِاللَّهِ وَمَا أَنْزَلْنَا عَلَىٰ عَبْدِنَا يَوْمَ الْفُرْقَانِ يَوْمَ الْتَقَى الْجَمْعَانِ ۗ وَاللَّهُ عَلَىٰ كُلِّ شَيْءٍ قَدِيرٌ"}, {"surah": 8, "ayah": 41, "ayah_end": null, "snippet": "يوم الفرقان يوم التقى الجمعان", "ayah_text": "۞ وَاعْلَمُوا أَنَّمَا غَنِمْتُمْ مِنْ شَيْءٍ فَأَنَّ لِلَّهِ خُمُسَهُ وَلِلرَّسُولِ وَلِذِي الْقُرْبَىٰ وَالْيَتَامَىٰ وَالْمَسَاكِينِ وَابْنِ السَّبِيلِ إِنْ كُنْتُمْ آمَنْتُمْ بِاللَّهِ وَمَا أَنْزَلْنَا عَلَىٰ عَبْدِنَا يَوْمَ الْفُرْقَانِ يَوْمَ الْتَقَى الْجَمْعَانِ ۗ وَاللَّهُ عَلَىٰ كُلِّ شَيْءٍ قَدِيرٌ"}, {"surah": 17, "ayah": 1, "ayah_end": null, "snippet": "أسرى بعبده ليلًا", "ayah_text": "بِسْمِ اللَّهِ الرَّحْمَٰنِ الرَّحِيمِ سُبْحَانَ الَّذِي أَسْرَىٰ بِعَبْدِهِ لَيْلًا مِنَ الْمَسْجِدِ الْحَرَامِ إِلَى الْمَسْجِدِ الْأَقْصَى الَّذِي بَارَكْنَا حَوْلَهُ لِنُرِيَهُ مِنْ آيَاتِنَا ۚ إِنَّهُ هُوَ السَّمِيعُ الْبَصِيرُ"}, {"surah": 18, "ayah": 1, "ayah_end": null, "snippet": "أنزل على عبده الكتاب", "ayah_text": "بِسْمِ اللَّهِ الرَّحْمَٰنِ الرَّحِيمِ الْحَمْدُ لِلَّهِ الَّذِي أَنْزَلَ عَلَىٰ عَبْدِهِ الْكِتَابَ وَلَمْ يَجْعَلْ لَهُ عِوَجًا ۜ"}, {"surah": 2, "ayah": 23, "ayah_end": null, "snippet": "مما نزلنا على عبدنا", "ayah_text": "وَإِنْ كُنْتُمْ فِي رَيْبٍ مِمَّا نَزَّلْنَا عَلَىٰ عَبْدِنَا فَأْتُوا بِسُورَةٍ مِنْ مِثْلِهِ وَادْعُوا شُهَدَاءَكُمْ مِنْ دُونِ اللَّهِ إِنْ كُنْتُمْ صَادِقِينَ"}, {"surah": 8, "ayah": 42, "ayah_end": null, "snippet": "ليقضي الله أمرًا كان مفعولًا", "ayah_text": "إِذْ أَنْتُمْ بِالْعُدْوَةِ الدُّنْيَا وَهُمْ بِالْعُدْوَةِ الْقُصْوَىٰ وَالرَّكْبُ أَسْفَلَ مِنْكُمْ ۚ وَلَوْ تَوَاعَدْتُمْ لَاخْتَلَفْتُمْ فِي الْمِيعَادِ ۙ وَلَٰكِنْ لِيَقْضِيَ اللَّهُ أَمْرًا كَانَ مَفْعُولًا لِيَهْلِكَ مَنْ هَلَكَ عَنْ بَيِّنَةٍ وَيَحْيَىٰ مَنْ حَيَّ عَنْ بَيِّنَةٍ ۗ وَإِنَّ اللَّهَ لَسَمِيعٌ عَلِيمٌ"}, {"surah": 8, "ayah": 43, "ayah_end": null, "snippet": "يريكهم الله في منامك قليلًا", "ayah_text": "إِذْ يُرِيكَهُمُ اللَّهُ فِي مَنَامِكَ قَلِيلًا ۖ وَلَوْ أَرَاكَهُمْ كَثِيرًا لَفَشِلْتُمْ وَلَتَنَازَعْتُمْ فِي الْأَمْرِ وَلَٰكِنَّ اللَّهَ سَلَّمَ ۗ إِنَّهُ عَلِيمٌ بِذَاتِ الصُّدُورِ"}, {"surah": 8, "ayah": 43, "ayah_end": null, "snippet": "لو أراكهم كثيرًا لفشلتم", "ayah_text": "إِذْ يُرِيكَهُمُ اللَّهُ فِي مَنَامِكَ قَلِيلًا ۖ وَلَوْ أَرَاكَهُمْ كَثِيرًا لَفَشِلْتُمْ وَلَتَنَازَعْتُمْ فِي الْأَمْرِ وَلَٰكِنَّ اللَّهَ سَلَّمَ ۗ إِنَّهُ عَلِيمٌ بِذَاتِ الصُّدُورِ"}, {"surah": 8, "ayah": 44, "ayah_end": null, "snippet": "يريكموهم إذ التقيتم في أعينكم قليلًا", "ayah_text": "وَإِذْ يُرِيكُمُوهُمْ إِذِ الْتَقَيْتُمْ فِي أَعْيُنِكُمْ قَلِيلًا وَيُقَلِّلُكُمْ فِي أَعْيُنِهِمْ لِيَقْضِيَ اللَّهُ أَمْرًا كَانَ مَفْعُولًا ۗ وَإِلَى اللَّهِ تُرْجَعُ الْأُمُورُ"}, {"surah": 8, "ayah": 44, "ayah_end": null, "snippet": "وإلى الله ترجع الأمور", "ayah_text": "وَإِذْ يُرِيكُمُوهُمْ إِذِ الْتَقَيْتُمْ فِي أَعْيُنِكُمْ قَلِيلًا وَيُقَلِّلُكُمْ فِي أَعْيُنِهِمْ لِيَقْضِيَ اللَّهُ أَمْرًا كَانَ مَفْعُولًا ۗ وَإِلَى اللَّهِ تُرْجَعُ الْأُمُورُ"}, {"surah": 8, "ayah": 45, "ayah_end": null, "snippet": "إذا لقيتم فئة فاثبتوا", "ayah_text": "يَا أَيُّهَا الَّذِينَ آمَنُوا إِذَا لَقِيتُمْ فِئَةً فَاثْبُتُوا وَاذْكُرُوا اللَّهَ كَثِيرًا لَعَلَّكُمْ تُفْلِحُونَ"}, {"surah": 8, "ayah": 45, "ayah_end": null, "snippet": "واذكروا الله كثيرًا", "ayah_text": "يَا أَيُّهَا الَّذِينَ آمَنُوا إِذَا لَقِيتُمْ فِئَةً فَاثْبُتُوا وَاذْكُرُوا اللَّهَ كَثِيرًا لَعَلَّكُمْ تُفْلِحُونَ"}], "others": [{"by": "زكوان", "start": "60:24", "end": "63:14", "point": "أرى في جعل الأنفال لله والرسول أبعادًا كثيرة: أولها تثبيت أن النصر لم يكن بأيديكم بل بيد رب العالمين، فما دام النصر منه فالأنفال له. وثانيها أن الله يربي المؤمنين على أنهم خرجوا لشيء أسمى من المال والعتاد، مع أنهم خرجوا أولًا للقافلة. وثالثها أنه ينقلهم من عادة الجاهلية، حيث يأخذ كل مقاتل ما تقع يده عليه، إلى تقسيم عادل. وكان ذلك اختبارًا لتسليمهم، وهو ليس سهلًا على من فقد أخًا أو رأى نفسه قد تعب في الحرب؛ وفيه أيضًا يخفف عنا الصورة المثالية المطلقة للصحابة، فهم بشر عندهم طمع وإحساس بالحق، لكن عندهم توبة ورحمة ونفس لوامة."}, {"by": "رضوان خياط", "start": "67:05", "end": "69:29", "point": "أجد في الصفحة الأخيرة إشارات نفسية جميلة في قضية الإدراك. أفعالنا ومواقفنا تتأثر بما نظنه واقعًا، لا بالواقع الخارجي وحده؛ فهناك صورة ذهنية قد تكون قريبة أو بعيدة، لكن فعلي يكون مدفوعًا بها. حين أرى أن الله أرى النبي ﷺ العدو قليلًا في المنام ثم أراهم للمؤمنين قليلًا عند اللقاء، أفهم كيف أن الصورة لو كانت على الواقع العددي لأدخلت الرعب والتردد والتنازع، لكن الصورة التي تشكلت دفعتهم إلى الإقدام."}, {"by": "عمرو", "start": "69:45", "end": "71:04", "point": "أرى في الصفحة الأخيرة أن الله يقرر للمسلمين أنه هو الذي رتب الأمر كله: أنتم في العدوة الدنيا وهم في العدوة القصوى، ولو تواعدتم لاختلفتم، وهو الذي أرى النبي المنام، وهو الذي جعل الفريقين يرى كل منهما الآخر قليلًا. الفضل والمنة لله في بدر. وأسأل هنا عن أهمية القائد في الإسلام؛ فمنام الرسول ﷺ، لو كان على صورة أخرى، كان يمكن أن يكون سببًا للفشل والتنازع، وهذا يدل على شدة التماهي بين القائد وجنده."}, {"by": "زكوان", "start": "74:06", "end": "75:06", "point": "أرى أن قيادة النبي ﷺ لم تكن قيادة دكتاتورية، بل قيادة فيها تشاور كثير، مع الحنكة والمعرفة والخبرة. كان يتشاور معهم لا فقط لإعطائهم الرأي، بل ليعلمهم وليجعل كل واحد منهم قائدًا. هذا المثال من القيادة نفتقده كثيرًا، وربما لذلك لا ننجح؛ نحن نحتاج قائدًا يعطي الناس هذا الإحساس ويتعلمون معه."}, {"by": "ياسر الصابوني", "start": "75:09", "end": "76:29", "point": "أتذكر موقف الحباب بن المنذر في بدر، حين سأل النبي ﷺ: أهو منزل أنزلكه الله أم هي الحرب والرأي والمشورة؟ جندي في موقف عصيب يتكلم بهذه الجرأة مع القائد الأعظم؛ وهذا لا يكون إلا لأن النبي ﷺ أعطاهم مساحة الكلام. كل إنسان شعر أنه مسؤول عن الجيش والمعركة والأمة، فتلك المسؤولية دفعته أن يتكلم ويبدي رأيه، والنبي ﷺ أخذ برأيه، كما أخذ برأي سلمان في الخندق."}, {"by": "محمد متولي", "start": "76:33", "end": "81:14", "point": "من وجهة نظري، قيادة الرسول ﷺ اعتمدت على التربية: حرية مع احترام، لا خوف. كان الصحابة يحترمونه لأنه نبي مرسل من الله، ومع ذلك لم يترددوا في الاختلاف الحميد للصالح العام، لا للجدال ولا لنزعة شخصية. فإذا كان الأمر وحيًا سلموا، وإذا كان رأيًا ومشورة أبدوا رأيهم. والرسول ﷺ كان يربي الجيل الذي سيحمل الدين بعده. وأرى أن صدق النية أساس؛ إذا صدقت النية لله ارتفع العمل ولازم الإنسان توفيق الله، حتى لو لم يوفق في الظاهر عوضه الله."}, {"by": "ياسر الصابوني", "start": "95:20", "end": "96:04", "point": "أقف عند الأمر بالثبات والذكر عند لقاء الفئة: إذا لقيتم فئة فاثبتوا واذكروا الله كثيرًا. هذا ما ينبغي أن نسعى إليه مع التقوى؛ أن نكون حريصين على رضا الله، فإذا زلت القدم وجدنا تكفير السيئات والمغفرة، ومع اللقاء يكون الثبات والذكر سبب الفلاح."}], "review": false, "review_reason": null, "surah": "سورة الأنفال", "_episode": "T1-e50", "segments": [{"type": "text", "text": "تبدأ الصفحة بالحديث عن الغنائم وكيفية اقتسامها [8:41]. وبداية السورة كانت قد أكدت أن ملكية الأنفال قد حُسمت: الأنفال لله والرسول. الله سبحانه وتعالى نزع ملكية الغنائم في المعركة وردها إلى الله ورسوله، ليخلص الأمر كله لله وللرسول، وليتجرد المؤمنون من كل ملابسات الأرض؛ فالمعركة لله، وفي سبيل الله، وطاعة لله، يخوضونها بأموالهم وأرواحهم، ويحكّمون الله ورسوله في أمرهم كله. لكن بعد أن استقر الإيمان، واستسلموا لله سبحانه وتعالى، وارتضوا حكمه، عاد فرد عليهم أربعة أخماس الغنيمة. المنهج القرآني يواجه الواقع الفعلي بأحكام منظمة. هناك غنائم، وهناك محاربون يجاهدون بالمال والنفس، ويتطوعون للجهاد، ويجهزون أنفسهم على نفقتهم الخاصة. فهذه حاجة واقعية لا تناقض رد ملكية الغنائم ابتداءً لله ورسوله. ولا أريد الدخول هنا في الروايات والآراء الفقهية التي اختلفت حول الفرق بين الأنفال"}, {"type": "q", "fragment": "إِذَا لَقِيتُمْ فِئَةً فَاثْبُتُوا", "surah": 8, "ayah": 45, "ayah_end": null}, {"type": "text", "text": "الخمس وكيفية تقسيمه: هل الخمس لله هو نفسه للرسول أم هو مستقل؟ وهل الخمس الذي للرسول ﷺ خاص به أم ينتقل لكل إمام للمسلمين بعده؟ في هذا العصر لا توجد قضية غنائم؛ لأنه لا توجد قضية جهاد بالمعنى المذكور في الآيات،"}, {"type": "q", "fragment": "وَلَوْ أَرَاكَهُمْ كَثِيرًا لَفَشِلْتُمْ", "surah": 8, "ayah": 43, "ayah_end": null}, {"type": "text", "text": "ندخل في هذه القضايا الفقهية حتى يحين وقتها، وينشأ المجتمع الإسلامي، ويواجه حالة جهاد فعلي. ثم ألتفت إلى البيان الإلهي في قوله: إن كنتم آمنتم بالله وما"}, {"type": "q", "fragment": "أَنْزَلَ عَلَىٰ عَبْدِهِ الْكِتَابَ", "surah": 18, "ayah": 1, "ayah_end": null}, {"type": "text", "text": "الفرقان [8:41]. وصف"}, {"type": "q", "fragment": "عَبْدِنَا", "surah": 8, "ayah": 41, "ayah_end": null}, {"type": "text", "text": "عظيم؛ فالعبودية لله هي حقيقة الإيمان، وهي أعلى مقام وأكرم مقام يبلغه الإنسان بتكريم من الله سبحانه وتعالى. وتكرر هذا الوصف في مواضع كثيرة، كقوله عن الإسراء بعبده [17:1]، وقوله عن إنزال الكتاب على عبده [18:1]، وقوله في التحدي بما نزل على عبده [2:23]. ومن اللطائف التدبرية وصف يوم بدر بيوم الفرقان. بدر فرقان بين الحق والباطل، وفرقان بين عهد الصبر والمصابرة والتجمع والانتظار قبل بدر، وعهد القوة والمبادأة والاندفاع بعد بدر. وهو فرقان بين عهدين في تاريخ البشرية: العهد قبل قيام النظام الإسلامي، والعهد بعد الانتصار والتمكين. وهو فرقان أيضًا بين تصورين لعوامل النصر وعوامل الهزيمة الحقيقية، لا العوامل الظاهرية فقط. وكانت بدر فرقانًا بمدلول آخر: فالحق لا يثبت، والباطل لا ينهار، بمجرد البيان النظري أو الحديث النظري عن الحق والباطل؛ بل لا بد أن يتحطم سلطان الباطل، وأن يعلو سلطان الحق. الإسلام منهج حركي واقعي معاش، لا مجرد نظرية للمعرفة أو الجدل أو المنطق. لا بد من فعل. ثم أرى من تدبير الله سبحانه وتعالى في المعركة أنه أرى رسول الله ﷺ الكافرين في الرؤيا قليلين، لا قوة لهم ولا وزن [8:43]، فأنبأ الصحابة برؤياه، فاستبشروا وتشجعوا على خوض المعركة بثقة، وهم الذين خرجوا على غير استعداد وعلى غير توقع للقتال. وحين التقى الجمعان وجهًا لوجه تكررت الرؤية النبوية الصادقة، وكانت من تدبير الله ما أغرى الفريقين بخوض المعركة [8:44]. واللفتة هنا أن المؤمنين يرون أعداءهم قليلين بعين الحقيقة، بوجود دعم الله سبحانه وتعالى والملائكة حولهم. والمشركون يرون المؤمنين قليلين بعين الظاهر؛ فالفارق العددي كان نحو ثلاثة أضعاف أو أكثر. ومن وراء ذلك تحققت غاية التدبير الإلهي، ووقع الأمر الذي أراد الله سبحانه وتعالى،"}, {"type": "q", "fragment": "وَإِلَى اللَّهِ تُرْجَعُ الْأُمُورُ", "surah": 8, "ayah": 44, "ayah_end": null}, {"type": "text", "text": "وفي نهاية الصفحة وما يليها إيحاءات وقواعد وتوجيهات سريعة: ضرورة الثبات عند لقاء العدو [8:45]، والاتصال بالله سبحانه وتعالى من خلال الذكر، وطاعة الله ورسوله، وتجنب النزاع والشقاق، والصبر على تكاليف المعركة، والحذر من البطر والرياء. وربما يتم نقاش بعضها في الأسبوع القادم عند الصفحة التالية إن أحيانا الله."}]}}, "t2": {"episode": "T2-e61", "date": "2025-06-20", "session_number": 61, "youtube_id": "f97-bNf0p7E", "start_s": 1697, "end_s": 2396, "start": "28:17", "end": "39:56", "presenter": "تميم", "unnamed": false, "voice_code": "Slate Owl", "confidence": "high", "text": "نتابع أيها الأحبة في تدبر الآيات ٤١ من ٤٥ اللي هي الصفحة ١٨٨ جزء العاشر في سورة الأمثال نحاول نظفها بالسياق العام للسورة بداية أن الخلفية الزمانية والسياق العام كما نعرف أنه تقريباً عندما نحكي بالسنة الثانية للهجرة غزوة البدر الكبرى التي وقعت في ١٧ رمضان الطور العام كان في المدينة المنورة لا تزاد في طور البناء السياسي والعسكري المسلمون كانوا يعانون من قلة العدد والعددة السياق السابق للآيات لهدول ٤١ من ٥٩ والهدف التربوي منهم كان تصليح دينة السائلين عن الغنائم فالغنيمة هي أداة لبناء المجتمع الإسلامي وليس بالثراء الشخصي بناء الهوية الإيمانية أي الصفات المستحقة بالنصر إضحاة تدبير الله عز وجل للنصر غيرما قلة العدد التحليل من الغنور والانفلاك بعد النصر يعني الطاعة والانتباه تثبيت القلب لمواصلة الجهاد والدعوة الآن السياق الخاص لهدول الآيات ٤١ من ٥٥ تشكل وحدة قرآنية متكاملة تعالج قواعد النصر في الإسلام عبر ثلاث مستويات فهي نزلت في سياق واحد الآية ٤١ هي عم تقلك الامددرات المالية تحليل طريقة تقسيم الغنائم ذلك بعد خلاف نعلمه نشأ بين الصحابة حول من يحق له الغنيمة فمن آمن هون المهون هون الجبس فمن آمن حقا بالله وبيوم بدر يوم الفرقان عليه أن يقبل هذا ولو خالف هواه عليه أن يقبل هذا ولو خالف هواه رقم ٢ للآيات ٢٤ إلى ٤٤ الرؤية والتقدير الإلهي فرح في تدبر الله المعركة رغم ضعف المسلمين الآية الأخيرة التوجيه الغباني لما بعد بدر في كل مواجهة قادمة بوضع قواعد الثبات واحد النصر ٢ لا تأن روح الإيمانية سمعنا سابقا في الآيات الله يبارك في خير أخونا الدكتور رمال بصفحة سابقة دعا الكافرين رب العالمين دعا الكافرين بتوبة أمر المؤمنين بالثبات والجهاد ثبتهم نفسيا بأن الله معهم الآن نبدأ نقفر سريعا على الآيات الآية ٤١ الآية ٤١ وعلموا الله يبارك في خير أخونا وسيم وعندما بدأنا بصورة الأنفال ذكرنا بأنها ناخلة قضية الأنفال تأتي من كلمة ناخلة وذكرنا التذكرة كانت جميلة جدا وفي محل أن رب العالمين بدأوا بسؤال والسؤال هو طريقة لجذب الانتباه ويسألونك عن الانفال طيبًا حاذر بالله ورسوله لكي نصنع طويل الآن اجت بعد ٤١ آية اجت تخصيص وذكرها الله يبارك في خير وكانت نقطة خارقة يعني ننتبه كلها فأحسن الله اللي معلم إذا كان معنا اليوم الآن عندما نبدأ بالآية ٤١ وعلموا بدأ في أول كلمة قضية عبودية قضية ليست مجرد تشريع مالي لكن هي اختبار إيماني وعلموا أنما غننتم تأتي الآية تأتي الآية لتقول لهم الآن وقد انتصرتم هذه هي أمانة الغناء قبطوا سلوككم المالي وفق شرع الله وكأن الله يقول لا تجعلوا أول نصر يقصدكم فلجعلوه بوابة لتنظيم رباني دقيق في المال والقياد والطاعة الآن عندنا باب الغميلة تمثل فتنة المال بعض النصر فلم يختبر في المال بعض النصر قد يكون فاته نصف الفتنة الآن أتيت لهم موضوع الخمس وكيف يوزع على فئات هذه الفئات واضحة لا تقاتل باليد لكنها تشكل قلب المجتمع الرسالة لسيدنا وحبيبنا صلى الله عليه وسلم القرابة للقربة الرعاية لليتامة الرحمة للمساكين التنية إلى أبن الصديق الدرس هنا أخواني النصر لا يحولك إلى متملك بل إلى خال للأمة بأموان النصر النصر يقيد بالشكر والانتظار ننتقل سريعا إلى الآية الأخرى لنقرئ إذ أنتم بالعدوى في الدنيا قبيت هنا إذا في مشال بس سبحان الله أننا نشارككم خريفة الموقع لأن الآية سبحان الله فيها وصف تخصيلي دقيق لمواقع المعركة وفي يعني دقة هندسية ومعنوية بشكل عام تقدر تعمل شوية زوم أخي عليها وضع تخصيلي المسلمون في موقع يعني أضعف الله سبحانه وتعالى وصفها في هذه المعركة بدقة هندسية ومعنوية جدا عالية المسلمون في موقع ضعف الماء بعيد لا خطة مسبقة لكن الله عز وزن جمع الفريقين ورغم غيار التركيب العسكري ليظهر وهنا النقطة الواضحة أن النصر هو قرار إلهي لا حساب عددي ليظهر عز وزن أن النصر هو قرار إلهي لا حساب عددي فلنحن إذ أنتم بالعدوى في الدنيا الجهة الأقرب للمدينة بشمال طبعا شمال بدر العدوى القصوى هي الجهة الأقرب إلى مكة جنوب بدر الركب أسفل منكم هي ثانثة القافلة في موقع أقرب إلى البحر ونحن ما كنا ننتبه البحر يعني مقصود البحر الأحمر بعيد عن ساعة المعركة والله سبحانه وتعالى رجع بها ولو تواعدتم لا اختلفتم يعني أدما أنتم ما كنتم مخططين فلنكون في اللقاء لكن الله سبحانه وتعالى بقبله وكرم وجوده ولأمر عظيم رسّب هذا الأمر وهو اسم أمره فمثل ما نشاهدون إخواني يعني الخرايط سبحان الله جداً وضحت أنا كل هذه السنوات العدوى الدنيا والعدوى القصوى وكيف الجهة والركب أسفل منكم فحبيت يعني شارككم بموضوع هذه الخريطة الصغيرة لعسى ولعلّا أنه يعني تكون المعاني تضوضح أكثر الدرس هنا المعركة المعركة ليست صدفة بل هو سيناريو إذا يعني صحى لي أني سمح لي أني أستخدم هذه الكلمة سيناريو رباني محتم لأن النصر من عند الله وليس من تدبير البشر لا تخاف من ضعفك إن كنت مع الله لا تبالغ ولا تركن إلى قوتك إن كنت مع نفسك سبحان الله الاتجاه والاتجاه المعاكس المعنيين لا تخاف من ضعفك إن كنت مع الله عز وجل ولا تركن إلى قوتك إن كنت مع نفسك الآية 43 سريعاً إذ يريكهم الله الرؤية من الله عز وجل لنبي صلى الله عليه وسلم كانت جزءاً من خطة نفسية ربانية لتثبيت المؤمنين لأنهم لو رأوا كثرتهم لو رأى كثرتهم لضعفت عذائهم الناس والله أراد أن يمهل النخوص للنصر بإبهار أن العدو قليل إلا القضية درس التهيئة النفسية من السنن الربانية في صناعة النصر والنصر يبدأ في القلب لا في ساحة القتال الآية 44 وإذ يريكمهم نكمل الله سخر الإدراك البصري سبحان الله شوف التعابير ودقت الإعجاز في اللغة وهذه واحدة من المعجزات لنبي صلى الله عليه وسلم اللي هو كان أمي بس الله صلى الله عليه وسلم وكان ينازل عليه القرآن من أين له هذا من عند لمه هذا هو رب العالمين الله سخر الإدراك البصري نفسه في المعركة فجعل المسلمين يرون العدو قليلاً والغكس كذلك فالهدف تحفيز المؤمنين واستدراج العدو هون حتى الدرس بيقلك أنه إدراكك البصري ليس محايل لكن هو يسير بأمر الله فتوكل على الله فيما ترى ولا تغتر بما تشرب الآن اجت الآية الأخيرة اللي كما قلنا أنه هي درس إلى يوم الكرقان غزة البدر اللي هي كانت فسطاتين كما نعرف اللي هي أنا إذا صحلي استخدم كلة الطوفان من هداك الوقت بلش كلة الطوفان لحتى تكون واضحة يا أيها الذين آمنوا قاعدة ثابتة في كل سباق احتفاظ ضرورة نفسية وصنظيمية ضرورة نفسية وصنظيمية ذكر الله ذكر الله كثيراً ليس فقط باللسان بل بالحضور الروحي واليقين لأن الذكر يبدد الخوف ويمنع القلب بالقمعنينة النصر ليس عسكرياً فقط بل روحي ونفسي وتربوي والآن إذا ما أثبت هذا أخي عالم أمر الواقع ونرى ما يمر به أخواننا وخاصة في غزة نعرف ذلك إذا ثبت الله قلبك إذا ثبتت قلبك يعني وذكرت ربك أتاك النصر ولو كنت وحدك الرسائل المشتفاة إخواني سلي عند المروأة إنه داركني الماء بعد النصر هو اختبار في الإيمان وخلاف المصلحة الغناء توزع بالميزان الله لا برغبة النفس الظروف الصعبة ليست من قياس النصر الله وحده هو من يقره وكيف تنتصر الإدراك والرؤية الله يهيئ النفس ويشخذ الحواس اختبات والذكر سلاح لا يرى لكنه أساس كل نصر ختاماً هذه الآيات لا تحكي فقط قصة مدر بل ترسم منهج النصر القرآني فكل من خضع لله وثبت قلبه وتكن ربه وتعامل بالعدل فهو على طريق النصر ولو تأخر زمنه ولو تأخر زمنه ننتقل وإياكم للحديث الشريف بالصفحة 357 قال لا تجتمع الأمة على ضرالة عن عبد الله بن مصعوب قال إن الله نظر في قلوب العباد فوجد قلب محمد عليه الصلاة والسلام خير قلوب العباد فاصطفاه لنفسه فاتعفه برسالته ثم نظر في قلوب العباد بعد قلب محمد عليه الصلاة والسلام فوجد قلوب أصحابه خير قلوب العباد فاجعلهم وزاراء نبيه يقاتلون على دينه فما رأى المسلمون حسناً فهو عند الله حسن وما رأوا سيئاً فهو عند الله سيئ نزعكم الله خير اللهم علمنا بما ينفعنا وانفعنا بما عذبتنا وزدنا عنا وشكر الله لكم وننتقل للأخ محمد والصفحة القادمة السلام عليكم", "tad": {"ayah_range": "8:41-8:45", "presenter": "تميم", "time_range": {"start": "28:17", "end": "39:56"}, "confidence": 0.96, "assignment": "match", "has_tadabbur": true, "tadabbur": "نحاول أن نربط الآيات بالسياق العام للسورة. الخلفية الزمانية كما نعرف هي السنة الثانية للهجرة، وغزوة بدر الكبرى التي وقعت في السابع عشر من رمضان. الطور العام كان أن المدينة المنورة لا تزال في طور البناء السياسي والعسكري، والمسلمون يعانون من قلة العدد والعُدة. والسياق السابق لهذه الآيات كان في تصحيح نية السائلين عن الغنائم؛ فالغنيمة أداة لبناء المجتمع الإسلامي وليست أداة للثراء الشخصي، وبناء الهوية الإيمانية، وبيان الصفات المستحقة للنصر، وإيضاح تدبير الله للنصر رغم قلة العدد، والتحذير من الغرور والانفلات بعد النصر، ثم تثبيت القلب لمواصلة الجهاد والدعوة. الآيات من 41 إلى 45 تشكل وحدة قرآنية متكاملة تعالج قواعد النصر في الإسلام على ثلاثة مستويات: الآية الأولى تتحدث عن الموارد المالية وطريقة تقسيم الغنائم بعد الخلاف الذي نشأ بين الصحابة حول من يحق له الغنيمة؛ فمن آمن حقًا بالله وبيوم الفرقان عليه أن يقبل حكم الله ولو خالف هواه. ثم الآيات 42 إلى 44 تعرض الرؤية والتقدير الإلهي للمعركة رغم ضعف المسلمين. ثم تأتي الآية 45 توجيهًا ربانيًا لما بعد بدر في كل مواجهة قادمة، بوضع قواعد الثبات والنصر وروح الإيمان. عندما تبدأ الآية بـ«واعلموا» [8:41] فهذا أمر عبودية، وليس مجرد تشريع مالي، بل اختبار إيماني. بدأت السورة أصلًا بسؤال عن الأنفال لجذب الانتباه، ثم بعد إحدى وأربعين آية يأتي التخصيص. كأن الله يقول: الآن وقد انتصرتم، هذه أمانة الغنيمة، فاضبطوا سلوككم المالي وفق شرع الله، ولا تجعلوا أول نصر يفسدكم، بل اجعلوه بوابة لتنظيم رباني دقيق في المال والقيادة والطاعة. الغنيمة تمثل فتنة المال بعد النصر، ومن لم يختبر في المال بعد النصر فقد يكون فاته نصف الفتنة. والخمس يوزع على فئات واضحة؛ هذه الفئات لا تقاتل باليد، لكنها تشكل قلب المجتمع: الرسالة للرسول صلى الله عليه وسلم، والقرابة لذوي القربى، والرعاية لليتامى، والرحمة للمساكين، والعناية بابن السبيل. الدرس هنا أن النصر لا يحولني إلى متملك، بل إلى خادم للأمة بأموال النصر؛ النصر يقيد بالشكر والانضباط. ثم في قوله: «إذ أنتم بالعدوة الدنيا» [8:42] يوجد وصف تفصيلي دقيق لمواقع المعركة، بدقة هندسية ومعنوية عالية. أحببت أن أشارك خريطة الموقع لأن الآية تذكر أن المسلمين كانوا في موضع ضعف: الماء بعيد، ولا خطة مسبقة، لكن الله جمع الفريقين رغم غياب التركيب العسكري المعتاد ليظهر أن النصر قرار إلهي لا حساب عددي. العدوة الدنيا هي الجهة الأقرب إلى المدينة شمال بدر، والعدوة القصوى الجهة الأقرب إلى مكة جنوب بدر، والركب أسفل منهم أي قافلة التجارة في موقع أقرب إلى البحر الأحمر بعيدًا عن ساحة المعركة. و«لو تواعدتم لاختلفتم» [8:42]؛ أي إنكم لو خططتم لهذا اللقاء لما اجتمعتم على هذا النحو، لكن الله بلطفه وكرمه رتب الأمر لأمر عظيم. الدرس أن المعركة ليست صدفة، بل هي، إن صح لي استعمال هذه الكلمة، سيناريو رباني محكم؛ لأن النصر من عند الله وليس من تدبير البشر فقط. فلا أخاف من ضعفي إن كنت مع الله، ولا أركن إلى قوتي إن كنت مع نفسي. في قوله: «إذ يريكهم الله في منامك قليلًا» [8:43] كانت الرؤيا من الله للنبي صلى الله عليه وسلم جزءًا من خطة نفسية ربانية لتثبيت المؤمنين؛ لأنهم لو رأوا كثرة العدو لضعفت عزائمهم، لكن الله أراد أن يمهد النفوس للنصر بإظهار العدو قليلًا. والدرس أن التهيئة النفسية من السنن الربانية في صناعة النصر؛ فالنصر يبدأ في القلب لا في ساحة القتال. ثم في قوله: «وإذ يريكموهم» [8:44] سخر الله الإدراك البصري نفسه في المعركة، فجعل المسلمين يرون العدو قليلًا، وجعل العدو يرى المسلمين قليلًا أيضًا؛ فالهدف تحفيز المؤمنين واستدراج العدو. والدرس هنا أن إدراكي البصري ليس محايدًا، بل هو يسير بأمر الله؛ فأتوكّل على الله فيما أرى، ولا أغتر بما أشاهد. ثم تأتي الآية الأخيرة: «يا أيها الذين آمنوا إذا لقيتم فئة فاثبتوا» [8:45]، وهي قاعدة ثابتة في كل سياق. الثبات ضرورة نفسية وتنظيمية، وذكر الله كثيرًا ليس باللسان فقط، بل بالحضور الروحي واليقين؛ لأن الذكر يبدد الخوف ويملأ القلب بالطمأنينة. النصر ليس عسكريًا فقط، بل روحي ونفسي وتربوي، ونحن نرى ذلك في واقع إخواننا، خاصة في غزة. إذا ثبت الله قلبك وذكرت ربك أتاك النصر ولو كنت وحدك. الرسائل المستفادة عندي: المال بعد النصر اختبار في الإيمان، والغنيمة توزع بميزان الله لا برغبة النفس، والظروف الصعبة ليست مقياس النصر، فالله وحده يقرر كيف تنتصر، والإدراك والرؤية يهيئ الله بهما النفس ويشحذ الحواس، والثبات والذكر سلاح لا يرى لكنه أساس كل نصر. هذه الآيات لا تحكي فقط قصة بدر، بل ترسم منهج النصر القرآني؛ فكل من خضع لله وثبت قلبه وذكر ربه وتعامل بالعدل فهو على طريق النصر ولو تأخر زمنه.", "key_message": "يريد ربي مني أن أقبل حكمه في المال والنصر، فأضبط الغنيمة بالعدل، وأثبت مع ذكره، وأرى تدبيره فوق حسابات الضعف والقوة.", "lessons": ["أتعامل مع المال بعد النصر كأمانة واختبار، لا كغنيمة شخصية للثراء.", "أقبل قسمة الله وحكمه ولو خالف هواي أو مصلحتي المباشرة.", "لا أجعل ضعف العدد والعُدة سببًا لليأس إذا كنت مع الله، ولا أغتر بالقوة إذا كنت مع نفسي.", "أدرك أن التهيئة النفسية والثبات الداخلي من سنن النصر قبل ساحة القتال.", "أكثر من ذكر الله حضورًا ويقينًا، لأنه يبدد الخوف ويثبت القلب.", "أقرأ بدر كمنهج متجدد للنصر، لا كقصة تاريخية منتهية."], "themes": ["الغنائم والأمانة المالية", "تدبير الله للنصر", "الثبات وذكر الله", "التربية بعد بدر"], "keywords": ["يوم الفرقان", "الخمس", "الغنائم", "العدوة الدنيا", "العدوة القصوى", "الركب", "الرؤيا", "الإدراك البصري", "الثبات", "ذكر الله"], "quran_quotes": [{"surah": 8, "ayah": 41, "ayah_end": null, "snippet": "واعلموا أنما غنمتم", "ayah_text": "۞ وَاعْلَمُوا أَنَّمَا غَنِمْتُمْ مِنْ شَيْءٍ فَأَنَّ لِلَّهِ خُمُسَهُ وَلِلرَّسُولِ وَلِذِي الْقُرْبَىٰ وَالْيَتَامَىٰ وَالْمَسَاكِينِ وَابْنِ السَّبِيلِ إِنْ كُنْتُمْ آمَنْتُمْ بِاللَّهِ وَمَا أَنْزَلْنَا عَلَىٰ عَبْدِنَا يَوْمَ الْفُرْقَانِ يَوْمَ الْتَقَى الْجَمْعَانِ ۗ وَاللَّهُ عَلَىٰ كُلِّ شَيْءٍ قَدِيرٌ"}, {"surah": 8, "ayah": 41, "ayah_end": null, "snippet": "يوم الفرقان يوم التقى الجمعان", "ayah_text": "۞ وَاعْلَمُوا أَنَّمَا غَنِمْتُمْ مِنْ شَيْءٍ فَأَنَّ لِلَّهِ خُمُسَهُ وَلِلرَّسُولِ وَلِذِي الْقُرْبَىٰ وَالْيَتَامَىٰ وَالْمَسَاكِينِ وَابْنِ السَّبِيلِ إِنْ كُنْتُمْ آمَنْتُمْ بِاللَّهِ وَمَا أَنْزَلْنَا عَلَىٰ عَبْدِنَا يَوْمَ الْفُرْقَانِ يَوْمَ الْتَقَى الْجَمْعَانِ ۗ وَاللَّهُ عَلَىٰ كُلِّ شَيْءٍ قَدِيرٌ"}, {"surah": 8, "ayah": 42, "ayah_end": null, "snippet": "إذ أنتم بالعدوة الدنيا", "ayah_text": "إِذْ أَنْتُمْ بِالْعُدْوَةِ الدُّنْيَا وَهُمْ بِالْعُدْوَةِ الْقُصْوَىٰ وَالرَّكْبُ أَسْفَلَ مِنْكُمْ ۚ وَلَوْ تَوَاعَدْتُمْ لَاخْتَلَفْتُمْ فِي الْمِيعَادِ ۙ وَلَٰكِنْ لِيَقْضِيَ اللَّهُ أَمْرًا كَانَ مَفْعُولًا لِيَهْلِكَ مَنْ هَلَكَ عَنْ بَيِّنَةٍ وَيَحْيَىٰ مَنْ حَيَّ عَنْ بَيِّنَةٍ ۗ وَإِنَّ اللَّهَ لَسَمِيعٌ عَلِيمٌ"}, {"surah": 8, "ayah": 42, "ayah_end": null, "snippet": "ولو تواعدتم لاختلفتم", "ayah_text": "إِذْ أَنْتُمْ بِالْعُدْوَةِ الدُّنْيَا وَهُمْ بِالْعُدْوَةِ الْقُصْوَىٰ وَالرَّكْبُ أَسْفَلَ مِنْكُمْ ۚ وَلَوْ تَوَاعَدْتُمْ لَاخْتَلَفْتُمْ فِي الْمِيعَادِ ۙ وَلَٰكِنْ لِيَقْضِيَ اللَّهُ أَمْرًا كَانَ مَفْعُولًا لِيَهْلِكَ مَنْ هَلَكَ عَنْ بَيِّنَةٍ وَيَحْيَىٰ مَنْ حَيَّ عَنْ بَيِّنَةٍ ۗ وَإِنَّ اللَّهَ لَسَمِيعٌ عَلِيمٌ"}, {"surah": 8, "ayah": 43, "ayah_end": null, "snippet": "إذ يريكهم الله في منامك قليلا", "ayah_text": "إِذْ يُرِيكَهُمُ اللَّهُ فِي مَنَامِكَ قَلِيلًا ۖ وَلَوْ أَرَاكَهُمْ كَثِيرًا لَفَشِلْتُمْ وَلَتَنَازَعْتُمْ فِي الْأَمْرِ وَلَٰكِنَّ اللَّهَ سَلَّمَ ۗ إِنَّهُ عَلِيمٌ بِذَاتِ الصُّدُورِ"}, {"surah": 8, "ayah": 44, "ayah_end": null, "snippet": "وإذ يريكموهم إذ التقيتم", "ayah_text": "وَإِذْ يُرِيكُمُوهُمْ إِذِ الْتَقَيْتُمْ فِي أَعْيُنِكُمْ قَلِيلًا وَيُقَلِّلُكُمْ فِي أَعْيُنِهِمْ لِيَقْضِيَ اللَّهُ أَمْرًا كَانَ مَفْعُولًا ۗ وَإِلَى اللَّهِ تُرْجَعُ الْأُمُورُ"}, {"surah": 8, "ayah": 45, "ayah_end": null, "snippet": "إذا لقيتم فئة فاثبتوا", "ayah_text": "يَا أَيُّهَا الَّذِينَ آمَنُوا إِذَا لَقِيتُمْ فِئَةً فَاثْبُتُوا وَاذْكُرُوا اللَّهَ كَثِيرًا لَعَلَّكُمْ تُفْلِحُونَ"}], "others": [{"by": "بلال الجاجة", "start": "65:20", "end": "71:27", "point": "قد يتبادر إلى الذهن تعارض بين ما في آل عمران من رؤية الكافرين للمؤمنين مثليهم رأي العين، وبين قوله هنا إن الله قلل المؤمنين في أعين المشركين. الخاطرة التي سمعتها من الدكتور راغب السرجاني أن هذا كله من جنود الله في بدر؛ فبداية المعركة رأى المؤمنون المشركين قليلين، حتى روي أن أحد الصحابة كان يراهم سبعين أو مئة، وكذلك رأى المشركون المسلمين قليلين، حتى قال أبو جهل في معناها إنهم كأكلة جزور. كان هذا قبل التحام الصفين. أما عند التحام الصفين فصار المشركون يرون المؤمنين مثليهم، فدخل عليهم الوهم البصري بقدر الله ليتم أمره. فهذا التقليل والتكثير نفسه من الجنود التي يسوقها الله للنصر.", "_timed": [{"start": "65:23", "end": "65:27", "text": "قد يتبادر إلى الذهن تعارض بين ما في آل عمران من رؤية الكافرين للمؤمنين مثليهم رأي العين، وبين قوله هنا إن الله قلل المؤمنين في أعين المشركين."}, {"start": "67:01", "end": "67:04", "text": "الخاطرة التي سمعتها من الدكتور راغب السرجاني أن هذا كله من جنود الله في بدر"}, {"start": "67:46", "end": "67:49", "text": "فبداية المعركة رأى المؤمنون المشركين قليلين، حتى روي أن أحد الصحابة كان يراهم سبعين أو مئة، وكذلك رأى المشركون المسلمين قليلين، حتى قال أبو جهل في معناها إنهم كأكلة جزور."}, {"start": "69:29", "end": "69:33", "text": "كان هذا قبل التحام الصفين."}, {"start": "69:49", "end": "69:51", "text": "أما عند التحام الصفين فصار المشركون يرون المؤمنين مثليهم، فدخل عليهم الوهم البصري بقدر الله ليتم أمره."}, {"start": "70:52", "end": "70:55", "text": "فهذا التقليل والتكثير نفسه من الجنود التي يسوقها الله للنصر."}]}, {"by": "ياسر الصابوني", "start": "79:28", "end": "89:48", "point": "الله يريد شيئًا ونحن نريد شيئًا؛ قد نحب أن تكون لنا غير ذات الشوكة، لكن عندما يقول الله إن الركب أسفل منكم ولو تواعدتم لاختلفتم في الميعاد، أفهم أن تدابير الله تدبر لي الأمر ولو كنت أريد خلاف ذلك؛ لأنه يعلم ما هو الأصلح لنا. لذلك أقول: اللهم إني أعوذ بك من تدبيري إلى تدبيرك.", "_timed": [{"start": "79:29", "end": "79:31", "text": "الله يريد شيئًا ونحن نريد شيئًا"}, {"start": "80:40", "end": "80:43", "text": "قد نحب أن تكون لنا غير ذات الشوكة، لكن عندما يقول الله إن الركب أسفل منكم ولو تواعدتم لاختلفتم في الميعاد، أفهم أن تدابير الله تدبر لي الأمر ولو كنت أريد خلاف ذلك"}, {"start": "86:56", "end": "86:58", "text": "لأنه يعلم ما هو الأصلح لنا."}, {"start": "87:49", "end": "87:53", "text": "لذلك أقول: اللهم إني أعوذ بك من تدبيري إلى تدبيرك."}]}], "tadabbur_timed": [{"start": "28:18", "end": "28:22", "text": "نحاول أن نربط الآيات بالسياق العام للسورة."}, {"start": "28:27", "end": "28:30", "text": "الخلفية الزمانية كما نعرف هي السنة الثانية للهجرة، وغزوة بدر الكبرى التي وقعت في السابع عشر من رمضان."}, {"start": "28:42", "end": "28:45", "text": "الطور العام كان أن المدينة المنورة لا تزال في طور البناء السياسي والعسكري، والمسلمون يعانون من قلة العدد والعُدة."}, {"start": "28:57", "end": "29:01", "text": "والسياق السابق لهذه الآيات كان في تصحيح نية السائلين عن الغنائم"}, {"start": "29:07", "end": "29:11", "text": "فالغنيمة أداة لبناء المجتمع الإسلامي وليست أداة للثراء الشخصي، وبناء الهوية الإيمانية، وبيان الصفات المستحقة للنصر، وإيضاح تدبير الله للنصر رغم قلة العدد، والتحذير من الغرور والانفلات بعد النصر، ثم تثبيت القلب لمواصلة الجهاد والدعوة."}, {"start": "29:53", "end": "29:57", "text": "الآيات من 41 إلى 45 تشكل وحدة قرآنية متكاملة تعالج قواعد النصر في الإسلام على ثلاثة مستويات: الآية الأولى تتحدث عن الموارد المالية وطريقة تقسيم الغنائم بعد الخلاف الذي نشأ بين الصحابة حول من يحق له الغنيمة"}, {"start": "30:36", "end": "30:38", "text": "فمن آمن حقًا بالله وبيوم الفرقان عليه أن يقبل حكم الله ولو خالف هواه."}, {"start": "30:44", "end": "30:47", "text": "ثم الآيات 42 إلى 44 تعرض الرؤية والتقدير الإلهي للمعركة رغم ضعف المسلمين."}, {"start": "30:55", "end": "30:59", "text": "ثم تأتي الآية 45 توجيهًا ربانيًا لما بعد بدر في كل مواجهة قادمة، بوضع قواعد الثبات والنصر وروح الإيمان."}, {"start": "31:12", "end": "31:17", "text": "عندما تبدأ الآية بـ«واعلموا» [8:41] فهذا أمر عبودية، وليس مجرد تشريع مالي، بل اختبار إيماني."}, {"start": "31:29", "end": "31:32", "text": "بدأت السورة أصلًا بسؤال عن الأنفال لجذب الانتباه، ثم بعد إحدى وأربعين آية يأتي التخصيص."}, {"start": "31:44", "end": "31:46", "text": "كأن الله يقول: الآن وقد انتصرتم، هذه أمانة الغنيمة، فاضبطوا سلوككم المالي وفق شرع الله، ولا تجعلوا أول نصر يفسدكم، بل اجعلوه بوابة لتنظيم رباني دقيق في المال والقيادة والطاعة."}, {"start": "32:12", "end": "32:16", "text": "الغنيمة تمثل فتنة المال بعد النصر، ومن لم يختبر في المال بعد النصر فقد يكون فاته نصف الفتنة."}, {"start": "32:28", "end": "32:32", "text": "والخمس يوزع على فئات واضحة"}, {"start": "32:36", "end": "32:39", "text": "هذه الفئات لا تقاتل باليد، لكنها تشكل قلب المجتمع: الرسالة للرسول صلى الله عليه وسلم، والقرابة لذوي القربى، والرعاية لليتامى، والرحمة للمساكين، والعناية بابن السبيل."}, {"start": "33:01", "end": "33:05", "text": "الدرس هنا أن النصر لا يحولني إلى متملك، بل إلى خادم للأمة بأموال النصر"}, {"start": "33:17", "end": "33:20", "text": "النصر يقيد بالشكر والانضباط."}, {"start": "33:20", "end": "33:24", "text": "ثم في قوله: «إذ أنتم بالعدوة الدنيا» [8:42] يوجد وصف تفصيلي دقيق لمواقع المعركة، بدقة هندسية ومعنوية عالية."}, {"start": "33:39", "end": "33:41", "text": "أحببت أن أشارك خريطة الموقع لأن الآية تذكر أن المسلمين كانوا في موضع ضعف: الماء بعيد، ولا خطة مسبقة، لكن الله جمع الفريقين رغم غياب التركيب العسكري المعتاد ليظهر أن النصر قرار إلهي لا حساب عددي."}, {"start": "34:15", "end": "34:19", "text": "العدوة الدنيا هي الجهة الأقرب إلى المدينة شمال بدر، والعدوة القصوى الجهة الأقرب إلى مكة جنوب بدر، والركب أسفل منهم أي قافلة التجارة في موقع أقرب إلى البحر الأحمر بعيدًا عن ساحة المعركة."}, {"start": "34:45", "end": "34:48", "text": "و«لو تواعدتم لاختلفتم» [8:42]"}, {"start": "34:48", "end": "34:51", "text": "أي إنكم لو خططتم لهذا اللقاء لما اجتمعتم على هذا النحو، لكن الله بلطفه وكرمه رتب الأمر لأمر عظيم."}, {"start": "35:04", "end": "35:09", "text": "الدرس أن المعركة ليست صدفة، بل هي، إن صح لي استعمال هذه الكلمة، سيناريو رباني محكم"}, {"start": "35:19", "end": "35:23", "text": "لأن النصر من عند الله وليس من تدبير البشر فقط."}, {"start": "35:27", "end": "35:31", "text": "فلا أخاف من ضعفي إن كنت مع الله، ولا أركن إلى قوتي إن كنت مع نفسي."}, {"start": "35:38", "end": "35:47", "text": "في قوله: «إذ يريكهم الله في منامك قليلًا» [8:43] كانت الرؤيا من الله للنبي صلى الله عليه وسلم جزءًا من خطة نفسية ربانية لتثبيت المؤمنين"}, {"start": "36:10", "end": "36:13", "text": "لأنهم لو رأوا كثرة العدو لضعفت عزائمهم، لكن الله أراد أن يمهد النفوس للنصر بإظهار العدو قليلًا."}, {"start": "36:25", "end": "36:30", "text": "والدرس أن التهيئة النفسية من السنن الربانية في صناعة النصر"}, {"start": "36:34", "end": "36:37", "text": "فالنصر يبدأ في القلب لا في ساحة القتال."}, {"start": "36:41", "end": "36:45", "text": "ثم في قوله: «وإذ يريكموهم» [8:44] سخر الله الإدراك البصري نفسه في المعركة، فجعل المسلمين يرون العدو قليلًا، وجعل العدو يرى المسلمين قليلًا أيضًا"}, {"start": "37:02", "end": "37:07", "text": "فالهدف تحفيز المؤمنين واستدراج العدو."}, {"start": "37:10", "end": "37:14", "text": "والدرس هنا أن إدراكي البصري ليس محايدًا، بل هو يسير بأمر الله"}, {"start": "37:21", "end": "37:25", "text": "فأتوكّل على الله فيما أرى، ولا أغتر بما أشاهد."}, {"start": "37:28", "end": "37:33", "text": "ثم تأتي الآية الأخيرة: «يا أيها الذين آمنوا إذا لقيتم فئة فاثبتوا» [8:45]، وهي قاعدة ثابتة في كل سياق."}, {"start": "37:49", "end": "37:52", "text": "الثبات ضرورة نفسية وتنظيمية، وذكر الله كثيرًا ليس باللسان فقط، بل بالحضور الروحي واليقين"}, {"start": "38:03", "end": "38:07", "text": "لأن الذكر يبدد الخوف ويملأ القلب بالطمأنينة."}, {"start": "38:11", "end": "38:14", "text": "النصر ليس عسكريًا فقط، بل روحي ونفسي وتربوي، ونحن نرى ذلك في واقع إخواننا، خاصة في غزة."}, {"start": "38:22", "end": "38:27", "text": "إذا ثبت الله قلبك وذكرت ربك أتاك النصر ولو كنت وحدك."}, {"start": "38:34", "end": "38:39", "text": "الرسائل المستفادة عندي: المال بعد النصر اختبار في الإيمان، والغنيمة توزع بميزان الله لا برغبة النفس، والظروف الصعبة ليست مقياس النصر، فالله وحده يقرر كيف تنتصر، والإدراك والرؤية يهيئ الله بهما النفس ويشحذ الحواس، والثبات والذكر سلاح لا يرى لكنه أساس كل نصر."}, {"start": "39:28", "end": "39:33", "text": "هذه الآيات لا تحكي فقط قصة بدر، بل ترسم منهج النصر القرآني"}, {"start": "39:42", "end": "39:46", "text": "فكل من خضع لله وثبت قلبه وذكر ربه وتعامل بالعدل فهو على طريق النصر ولو تأخر زمنه."}], "review": false, "review_reason": null, "surah": "الأنفال", "_episode": "T2-e61", "segments": [{"type": "text", "text": "نحاول أن نربط الآيات بالسياق العام للسورة. الخلفية الزمانية كما نعرف هي السنة الثانية للهجرة، وغزوة بدر الكبرى التي وقعت في السابع عشر من رمضان. الطور العام كان أن المدينة المنورة لا تزال في طور البناء السياسي والعسكري، والمسلمون يعانون من قلة العدد والعُدة. والسياق السابق لهذه الآيات كان في تصحيح نية السائلين عن الغنائم؛ فالغنيمة أداة لبناء المجتمع الإسلامي وليست أداة للثراء الشخصي، وبناء الهوية الإيمانية، وبيان الصفات المستحقة للنصر، وإيضاح تدبير الله للنصر رغم قلة العدد، والتحذير من الغرور والانفلات بعد النصر، ثم تثبيت القلب لمواصلة الجهاد والدعوة. الآيات من 41 إلى 45 تشكل وحدة قرآنية متكاملة تعالج قواعد النصر في الإسلام على ثلاثة مستويات: الآية الأولى تتحدث عن الموارد المالية وطريقة تقسيم الغنائم بعد الخلاف الذي نشأ بين الصحابة حول من يحق له الغنيمة؛ فمن آمن حقًا بالله وبيوم الفرقان عليه أن يقبل حكم الله ولو خالف هواه. ثم الآيات 42 إلى 44 تعرض الرؤية والتقدير الإلهي للمعركة رغم ضعف المسلمين. ثم تأتي الآية 45 توجيهًا ربانيًا لما بعد بدر في كل مواجهة قادمة، بوضع قواعد الثبات والنصر وروح الإيمان. عندما تبدأ الآية بـ"}, {"type": "q", "fragment": "وَاعْلَمُوا", "surah": 8, "ayah": 41, "ayah_end": null}, {"type": "text", "text": "فهذا أمر عبودية، وليس مجرد تشريع مالي، بل اختبار إيماني. بدأت السورة أصلًا بسؤال عن الأنفال لجذب الانتباه، ثم بعد إحدى وأربعين آية يأتي التخصيص. كأن الله يقول: الآن وقد انتصرتم، هذه أمانة الغنيمة، فاضبطوا سلوككم المالي وفق شرع الله، ولا تجعلوا أول نصر يفسدكم، بل اجعلوه بوابة لتنظيم رباني دقيق في المال والقيادة والطاعة. الغنيمة تمثل فتنة المال بعد النصر، ومن لم يختبر في المال بعد النصر فقد يكون فاته نصف الفتنة. والخمس يوزع على فئات واضحة؛ هذه الفئات لا تقاتل باليد، لكنها تشكل قلب المجتمع: الرسالة للرسول صلى الله عليه وسلم، والقرابة لذوي القربى، والرعاية لليتامى، والرحمة للمساكين، والعناية بابن السبيل. الدرس هنا أن النصر لا يحولني إلى متملك، بل إلى خادم للأمة بأموال النصر؛ النصر يقيد بالشكر والانضباط. ثم في قوله:"}, {"type": "q", "fragment": "إِذْ أَنْتُمْ بِالْعُدْوَةِ الدُّنْيَا", "surah": 8, "ayah": 42, "ayah_end": null}, {"type": "text", "text": "يوجد وصف تفصيلي دقيق لمواقع المعركة، بدقة هندسية ومعنوية عالية. أحببت أن أشارك خريطة الموقع لأن الآية تذكر أن المسلمين كانوا في موضع ضعف: الماء بعيد، ولا خطة مسبقة، لكن الله جمع الفريقين رغم غياب التركيب العسكري المعتاد ليظهر أن النصر قرار إلهي لا حساب عددي. العدوة الدنيا هي الجهة الأقرب إلى المدينة شمال بدر، والعدوة القصوى الجهة الأقرب إلى مكة جنوب بدر، والركب أسفل منهم أي قافلة التجارة في موقع أقرب إلى البحر الأحمر بعيدًا عن ساحة المعركة. و"}, {"type": "q", "fragment": "وَلَوْ تَوَاعَدْتُمْ لَاخْتَلَفْتُمْ", "surah": 8, "ayah": 42, "ayah_end": null}, {"type": "text", "text": "؛ أي إنكم لو خططتم لهذا اللقاء لما اجتمعتم على هذا النحو، لكن الله بلطفه وكرمه رتب الأمر لأمر عظيم. الدرس أن المعركة ليست صدفة، بل هي، إن صح لي استعمال هذه الكلمة، سيناريو رباني محكم؛ لأن النصر من عند الله وليس من تدبير البشر فقط. فلا أخاف من ضعفي إن كنت مع الله، ولا أركن إلى قوتي إن كنت مع نفسي. في قوله:"}, {"type": "q", "fragment": "إِذْ يُرِيكَهُمُ اللَّهُ فِي مَنَامِكَ قَلِيلًا", "surah": 8, "ayah": 43, "ayah_end": null}, {"type": "text", "text": "كانت الرؤيا من الله للنبي صلى الله عليه وسلم جزءًا من خطة نفسية ربانية لتثبيت المؤمنين؛ لأنهم لو رأوا كثرة العدو لضعفت عزائمهم، لكن الله أراد أن يمهد النفوس للنصر بإظهار العدو قليلًا. والدرس أن التهيئة النفسية من السنن الربانية في صناعة النصر؛ فالنصر يبدأ في القلب لا في ساحة القتال. ثم في قوله:"}, {"type": "q", "fragment": "وَإِذْ يُرِيكُمُوهُمْ", "surah": 8, "ayah": 44, "ayah_end": null}, {"type": "text", "text": "سخر الله الإدراك البصري نفسه في المعركة، فجعل المسلمين يرون العدو قليلًا، وجعل العدو يرى المسلمين قليلًا أيضًا؛ فالهدف تحفيز المؤمنين واستدراج العدو. والدرس هنا أن إدراكي البصري ليس محايدًا، بل هو يسير بأمر الله؛ فأتوكّل على الله فيما أرى، ولا أغتر بما أشاهد. ثم تأتي الآية الأخيرة:"}, {"type": "q", "fragment": "أَيُّهَا الَّذِينَ آمَنُوا إِذَا لَقِيتُمْ فِئَةً فَاثْبُتُوا", "surah": 8, "ayah": 45, "ayah_end": null}, {"type": "text", "text": "، وهي قاعدة ثابتة في كل سياق. الثبات ضرورة نفسية وتنظيمية، وذكر الله كثيرًا ليس باللسان فقط، بل بالحضور الروحي واليقين؛ لأن الذكر يبدد الخوف ويملأ القلب بالطمأنينة. النصر ليس عسكريًا فقط، بل روحي ونفسي وتربوي، ونحن نرى ذلك في واقع إخواننا، خاصة في غزة. إذا ثبت الله قلبك وذكرت ربك أتاك النصر ولو كنت وحدك. الرسائل المستفادة عندي: المال بعد النصر اختبار في الإيمان، والغنيمة توزع بميزان الله لا برغبة النفس، والظروف الصعبة ليست مقياس النصر، فالله وحده يقرر كيف تنتصر، والإدراك والرؤية يهيئ الله بهما النفس ويشحذ الحواس، والثبات والذكر سلاح لا يرى لكنه أساس كل نصر. هذه الآيات لا تحكي فقط قصة بدر، بل ترسم منهج النصر القرآني؛ فكل من خضع لله وثبت قلبه وذكر ربه وتعامل بالعدل فهو على طريق النصر ولو تأخر زمنه."}]}}}