{"page": 416, "surahs": [{"num": 32, "ar": "السجدة", "en": "As-Sajda"}], "juz": 21, "quran": null, "quran_com": "https://quran.com/page/416", "t1": {"episode": "T1-e111", "date": "2023-01-13", "session_number": 111, "youtube_id": "L2EuNmuNogM", "start_s": 1930, "end_s": 2227, "start": "32:10", "end": "37:07", "presenter": "رامي", "unnamed": false, "voice_code": "Hazel Owl", "confidence": "low", "text": "جزاكم الله خير أخي ماد حاول أنا أختصر نحن للوقت جزاكم الله خير بسم الله الرحمن الرحيم نتابع أيها الأخوة الأخاضر والأخوات في سورة السجد الجزء 21 نحن بالصفحة 416 الآيات من 12 إلى 20 اللي هننتسأ آيات طبعاً هي السورة مثل ما أفضل الدكتور بالبداية هي سورة مكية لكن أنا حسب فهمي ما عدى الآيات اللي هي بهذه الصفحة من 16 إلى 20 فهي مدنية والله عنا طبعاً هذه الصفحة تتابع بأن تبين للناس أنهم مبعوثون ومحاسبون على أعمالهم فهي ترد على إنكار الكافرين البعث بذكر تفاصيل الموت ولقائهم ربهم وطلبهم منه الرجوع إلى الدنيا ليعملوا صالحا هي هون المشكلة أنه عند آخر لحظة ربي أرجعني لعلي أعملوا صالحاً لهذا المعنى العام يعني وفي آية يعني قرآنية هي ما تستحضرني الآن إذا أحد الأخوة بس بيتكرم يحط على المجموعة العامة بمعنى أنه هون رب العالمين كان يتحدى أنه حتى ولو رجع الإنسان فهو سيكون وسيتابع الضلالة تبعه فللأسف يعني هون الإنسان هو هون كلمة الإجرام المجرمون وقت اللي وردت بالكلمة ولو ترى إذ المجرمونة زاكم الله خير أخي طارق ولو شاء تعالى لهذا الناس جميعاً فلن يختلف منهم أحد لكن حق القول منه تعالى بأن يعبد في جهنم الذين اختاروا العصيان بعد التكليف خالدين فيها منسيين بسبب تكديبهم ونسيانهم أما المؤمنون فهم يسجدون ويسبحون بحمد ربهم رقم 2 ولا يستكبرون رقم 3 رقم 4 ويدعون ربهم خوفاً وطمعاً وينفقون رقم 5 فسبحان الله هون يدعون ربهم نحو الأعلى إلى خالقنا خوفاً وطمعاً وينفقون تجاه البشر يعني شاقوني وأفقي طبعاً الإنفاق هو قد يكون بالصدقة قد يكون بالكلمة الطيبة قد يكون بالعلم قد يكون بأي شيء يستطيع أن يقوم فيه الإنسان فلا يعلم أحد عن عظم ما أخفى الله لنا في جنات النعيم فللمؤمنين جنات المأوى نزلا وأما الذين فسقوا فمأواهم النار كلما أرادوا أن يخرجوا منها أعيدوا فيها وقيل لهم تقريعاً وتوبيخاً وذوقوا عذاب النار الذي كنتم به تكذبون يعني هون لو نشوف عظمة الخالق أنتوا كذبتوا أنتوا نسيتوا فما يوم القيام والعياذ بالله نسيناكم وذوقوا عذاب النار الذي كنتم به تكذبون لأنه كلما أرادوا أن يخرجوا منها أعيدوا فيها وفي الدنيا يضيقهم العذاب لعلهم يرجعون فيتدبرون آياته قبل أن يأتي يوم لا رجوع فيه كلمات سريعة حبيت أوقف عليها بس إختصاراً للوقت يعني سبحان الله ولو ترى إذن مجرمون المجرمون هون الإنسان أجرم بنفسه ناكسوا رؤوسهم الإنسان المجرم والعياذ بالله وتصور أنه فيه شخص حرامي مجرم قاتل يعني وطبعاً وعند الشرطة تقبض عليه والناس قاعدة عم تتفرج عليه يكون هو مذلول يكون هو يعني ناكس رأسه وبدأ يروح على المحكمة أو بدأ يروح يعني على القسم التحقيق أو أو أو فهون ناكسوا رؤوسهم عند ربهم ربنا أبصرنا وسمعنا أبصرنا وسمعنا طبعاً قوة البصر وقوة السمع وهون لاحظوا كلمة أبصرنا أجت قبل سمعنا لأنه نحن في الحياة والدنيا كان كل شيء عننا واضح وسمعنا يعني شاهدنا وسمعنا سبحان الله يعني أنا حاولت أختصر كثير بس كسباً للوقت اللهم صل على النبي التوجيهات الإنسان يعني يعمل صالحاً قبل أن تتمنى لا صمح الله نتمنى عملها ولا نستطيع فإن رجعنا نعمل صالحاً إنا موقنون طبعاً الهداية بيد الله عز وجل ولو شئنا لآتينا كل نفس هداها طبعاً يكون لكل مننا خبيئة عمل صالح فلنعمل صالحاً ولا يطلع عليه أحد إلا الله فلا تعلم نفس ما أخفي لهم من قربة آية جزاء من ما كانوا يعملون جزاكم الله خير وأمل أني يعني معلش سامحوني على الأختصار بس أنا حاولت أني كسباً للوقت وجزاكم الله خير والسلام عليكم", "tad": {"ayah_range": "32:12-32:20", "presenter": "رامي", "time_range": {"start": "32:10", "end": "37:07"}, "confidence": 0.95, "assignment": "match", "has_tadabbur": true, "tadabbur": "أتابع في سورة السجدة، في الصفحة التي تضم الآيات من 12 إلى 20. السورة مكية، وبحسب فهمي فإن الآيات من 16 إلى 20 مدنية، والله أعلم. هذه الصفحة تتابع بيان أن الناس مبعوثون ومحاسبون على أعمالهم، وترد على إنكار الكافرين للبعث بذكر تفاصيل الموت ولقاء الرب وطلب الرجوع إلى الدنيا ليعملوا صالحاً. المشكلة أن الإنسان عند آخر لحظة يقول بمعنى: رب ارجعني لأعمل صالحاً [23:99-100]. وأتذكر معنى آية لا أستحضر نصها الآن، أن الإنسان لو رُدّ إلى الدنيا لتابع ضلاله. تبدأ الصورة بـ«المجرمين» [32:12]، والإنسان هنا أجرم في حق نفسه. ولو شاء الله لهدى الناس جميعاً، فما اختلف منهم أحد، لكن حق القول منه أن تمتلئ جهنم ممن اختار العصيان بعد التكليف، فيخلدون فيها منسيين بسبب تكذيبهم ونسيانهم. أما المؤمنون فتظهر صفاتهم: يسجدون، ويسبحون بحمد ربهم، ولا يستكبرون، ويدعون ربهم خوفاً وطمعاً، وينفقون. سبحان الله، أرى هنا بعداً شاقولياً وأفقياً؛ يدعون ربهم إلى الأعلى، إلى خالقنا، خوفاً وطمعاً، وينفقون تجاه البشر. والإنفاق قد يكون بالصدقة، وقد يكون بالكلمة الطيبة، وقد يكون بالعلم، وقد يكون بأي شيء يستطيع الإنسان أن يقوم به. ثم لا يعلم أحد عظم ما أخفى الله لهم من النعيم وقرة الأعين [32:17]. للمؤمنين جنات المأوى نزلاً، وأما الذين فسقوا فمأواهم النار؛ كلما أرادوا أن يخرجوا منها أعيدوا فيها، ويقال لهم تقريعاً وتوبيخاً: ذوقوا عذاب النار الذي كنتم به تكذبون [32:20]. كذبتم ونسيتم، فيأتي يوم القيامة والعياذ بالله: نُسيتم، وذقتم عذاب النار الذي كنتم تكذبون به. وفي الدنيا يذيقهم الله العذاب لعلهم يرجعون، فيتدبرون آياته قبل أن يأتي يوم لا رجوع فيه. وأتوقف سريعاً عند «ولو ترى إذ المجرمون ناكسو رؤوسهم» [32:12]. أتخيل إنساناً سارقاً أو قاتلاً تقبض عليه الشرطة والناس ينظرون إليه؛ يكون مذلولاً، ناكس الرأس، ذاهباً إلى التحقيق أو المحكمة. فكيف إذا كان ناكس رأسه عند ربه؟ ثم يقولون: «ربنا أبصرنا وسمعنا» [32:12]. لفتني أن البصر جاء قبل السمع؛ كأن كل شيء صار أمامهم واضحاً، شاهدوا وسمعوا. والتوجيه العملي لي أن أعمل صالحاً قبل أن أتمنى العمل ولا أستطيع، وقبل أن أقول: أرجعوني نعمل صالحاً إنا موقنون. والهداية بيد الله عز وجل، فلأجعل لي خبيئة عمل صالح لا يطلع عليها أحد إلا الله، فهناك «فلا تعلم نفس ما أخفي لهم من قرة أعين» [32:17] جزاءً بما كانوا يعملون.", "key_message": "يريد ربي مني أن أصدق بالبعث قبل فوات الأوان، وأن أترك الإجرام في حق نفسي إلى سجود خاشع وعمل صالح خفي وإنفاق نافع.", "lessons": ["لا أنتظر لحظة الندم عند الموت أو القيامة لأتمنى الرجوع والعمل الصالح.", "أفهم أن الإجرام الحقيقي يبدأ بإجرام الإنسان في حق نفسه بتكذيب الآخرة.", "أجمع بين السجود والتسبيح وترك الاستكبار، فهذه علامة الإيمان بالآيات.", "أدعو الله خوفاً وطمعاً، وأجعل لعبادتي بعداً يصل إلى الناس بالإنفاق والكلمة والعلم.", "أحرص على خبيئة عمل لا يطلع عليها إلا الله رجاء الجزاء المخفي.", "أتدبر عذاب الدنيا بوصفه إنذاراً ورحمة تفتح باب الرجوع قبل يوم لا رجوع فيه."], "themes": ["مشهد الحساب والندم", "صفات المؤمنين الخاشعين", "السجود وترك الاستكبار", "الجزاء المخفي والنار"], "keywords": ["المجرمون", "ناكسي رؤوسهم", "أبصرنا وسمعنا", "فارجعنا", "خروا سجدا", "لا يستكبرون", "خوفا وطمعا", "ينفقون", "قرة أعين", "جنات المأوى", "مأواهم النار"], "quran_quotes": [{"surah": 32, "ayah": 12, "ayah_end": null, "snippet": "المجرمون ناكسو رؤوسهم", "ayah_text": "وَلَوْ تَرَىٰ إِذِ الْمُجْرِمُونَ نَاكِسُو رُءُوسِهِمْ عِنْدَ رَبِّهِمْ رَبَّنَا أَبْصَرْنَا وَسَمِعْنَا فَارْجِعْنَا نَعْمَلْ صَالِحًا إِنَّا مُوقِنُونَ"}, {"surah": 32, "ayah": 12, "ayah_end": null, "snippet": "ربنا أبصرنا وسمعنا", "ayah_text": "وَلَوْ تَرَىٰ إِذِ الْمُجْرِمُونَ نَاكِسُو رُءُوسِهِمْ عِنْدَ رَبِّهِمْ رَبَّنَا أَبْصَرْنَا وَسَمِعْنَا فَارْجِعْنَا نَعْمَلْ صَالِحًا إِنَّا مُوقِنُونَ"}, {"surah": 32, "ayah": 13, "ayah_end": null, "snippet": "لو شئنا لآتينا كل نفس هداها", "ayah_text": "وَلَوْ شِئْنَا لَآتَيْنَا كُلَّ نَفْسٍ هُدَاهَا وَلَٰكِنْ حَقَّ الْقَوْلُ مِنِّي لَأَمْلَأَنَّ جَهَنَّمَ مِنَ الْجِنَّةِ وَالنَّاسِ أَجْمَعِينَ"}, {"surah": 32, "ayah": 14, "ayah_end": null, "snippet": "فذوقوا بما نسيتم", "ayah_text": "فَذُوقُوا بِمَا نَسِيتُمْ لِقَاءَ يَوْمِكُمْ هَٰذَا إِنَّا نَسِينَاكُمْ ۖ وَذُوقُوا عَذَابَ الْخُلْدِ بِمَا كُنْتُمْ تَعْمَلُونَ"}, {"surah": 32, "ayah": 15, "ayah_end": null, "snippet": "خروا سجدا", "ayah_text": "إِنَّمَا يُؤْمِنُ بِآيَاتِنَا الَّذِينَ إِذَا ذُكِّرُوا بِهَا خَرُّوا سُجَّدًا وَسَبَّحُوا بِحَمْدِ رَبِّهِمْ وَهُمْ لَا يَسْتَكْبِرُونَ ۩"}, {"surah": 32, "ayah": 15, "ayah_end": null, "snippet": "وهم لا يستكبرون", "ayah_text": "إِنَّمَا يُؤْمِنُ بِآيَاتِنَا الَّذِينَ إِذَا ذُكِّرُوا بِهَا خَرُّوا سُجَّدًا وَسَبَّحُوا بِحَمْدِ رَبِّهِمْ وَهُمْ لَا يَسْتَكْبِرُونَ ۩"}, {"surah": 32, "ayah": 16, "ayah_end": null, "snippet": "يدعون ربهم خوفا وطمعا", "ayah_text": "تَتَجَافَىٰ جُنُوبُهُمْ عَنِ الْمَضَاجِعِ يَدْعُونَ رَبَّهُمْ خَوْفًا وَطَمَعًا وَمِمَّا رَزَقْنَاهُمْ يُنْفِقُونَ"}, {"surah": 32, "ayah": 17, "ayah_end": null, "snippet": "فلا تعلم نفس ما أخفي", "ayah_text": "فَلَا تَعْلَمُ نَفْسٌ مَا أُخْفِيَ لَهُمْ مِنْ قُرَّةِ أَعْيُنٍ جَزَاءً بِمَا كَانُوا يَعْمَلُونَ"}, {"surah": 32, "ayah": 19, "ayah_end": null, "snippet": "جنات المأوى نزلا", "ayah_text": "أَمَّا الَّذِينَ آمَنُوا وَعَمِلُوا الصَّالِحَاتِ فَلَهُمْ جَنَّاتُ الْمَأْوَىٰ نُزُلًا بِمَا كَانُوا يَعْمَلُونَ"}, {"surah": 32, "ayah": 20, "ayah_end": null, "snippet": "كلما أرادوا أن يخرجوا", "ayah_text": "وَأَمَّا الَّذِينَ فَسَقُوا فَمَأْوَاهُمُ النَّارُ ۖ كُلَّمَا أَرَادُوا أَنْ يَخْرُجُوا مِنْهَا أُعِيدُوا فِيهَا وَقِيلَ لَهُمْ ذُوقُوا عَذَابَ النَّارِ الَّذِي كُنْتُمْ بِهِ تُكَذِّبُونَ"}, {"surah": 23, "ayah": 99, "ayah_end": 100, "snippet": "رب ارجعون لعلي أعمل صالحا", "ayah_text": "حَتَّىٰ إِذَا جَاءَ أَحَدَهُمُ الْمَوْتُ قَالَ رَبِّ ارْجِعُونِ لَعَلِّي أَعْمَلُ صَالِحًا فِيمَا تَرَكْتُ ۚ كَلَّا ۚ إِنَّهَا كَلِمَةٌ هُوَ قَائِلُهَا ۖ وَمِنْ وَرَائِهِمْ بَرْزَخٌ إِلَىٰ يَوْمِ يُبْعَثُونَ"}, {"surah": 7, "ayah": 146, "ayah_end": null, "snippet": "سأصرف عن آياتي الذين يتكبرون", "ayah_text": "سَأَصْرِفُ عَنْ آيَاتِيَ الَّذِينَ يَتَكَبَّرُونَ فِي الْأَرْضِ بِغَيْرِ الْحَقِّ وَإِنْ يَرَوْا كُلَّ آيَةٍ لَا يُؤْمِنُوا بِهَا وَإِنْ يَرَوْا سَبِيلَ الرُّشْدِ لَا يَتَّخِذُوهُ سَبِيلًا وَإِنْ يَرَوْا سَبِيلَ الْغَيِّ يَتَّخِذُوهُ سَبِيلًا ۚ ذَٰلِكَ بِأَنَّهُمْ كَذَّبُوا بِآيَاتِنَا وَكَانُوا عَنْهَا غَافِلِينَ"}], "others": [{"by": "وائل حمدوش", "start": "08:05", "end": "09:35", "point": "أربط اسم السورة بآية السجدة: لا يمكن أن أتلقى الكتاب ولا أن أكون مؤمناً إلا إذا سجدت لله واقتربت، أي خضعت لله وتركت الاستكبار. السجود هنا سجود كوني لله كما تسجد له المخلوقات، ولذلك يذكر الله المؤمنين بأنهم إذا ذُكّروا بآياته خروا سجداً وسبحوا بحمد ربهم وهم لا يستكبرون."}, {"by": "نذير", "start": "68:34", "end": "74:10", "point": "أتوقف عند قوله إنما يؤمن بآياتنا الذين إذا ذكروا بها خروا سجداً، وعند ختمها بأنهم لا يستكبرون. ذكرتني بسورة الأعراف: «سأصرف عن آياتي الذين يتكبرون» [7:146]؛ كأن الإيمان والاستكبار نقيضان. وعلى كثرة من ناقشتهم ممن ألحدوا أو تنكبوا عن صراط الله، أرى صفة مشتركة بينهم جميعاً: الكبر، ولا أزكي نفسي طرفة عين. حتى المدارس المعاصرة كالإلحاد والليبرالية والفردانية والإنسانوية يجمعها تقديس الذات والأنا وسحب القداسة من أي إله أو فكرة. لذلك لا يموت الإنسان في هذه التصورات من أجل فكرة، ولا جهاد ولا تضحية بالنفس. أما السجود فهو أعظم خضوع، وبقدر ما أسجد وأضع نفسي يقترب إيماني من الله. والآية التالية عن تجافي الجنوب عن المضاجع تأتي عكس رغائب الإنسان تماماً؛ فلا يؤمن المرء حق الإيمان حتى يضع نفسه أمام الفكرة الأسمى: الدين ووجود الإله."}, {"by": "ياسر صابوني", "start": "90:35", "end": "91:50", "point": "أتعلم من هذه المقارنات في سورة السجدة أن الإنسان لا يخرج من إلحاده وكبره بمجرد التفكير العقلي، بل لا بد أن يتحرك القلب ليناجي ربه. تحرق الآيات قلوبنا بصورة الذين تتجافى جنوبهم عن المضاجع، ثم تأتي «فلا تعلم نفس ما أخفي لهم» [32:17]؛ فكما أخفوا عبادتهم في جوف الليل أخفى الله عن الخلق ما أعد لهم، والجزاء من جنس العمل."}], "review": false, "review_reason": null, "surah": "السجدة", "_episode": "T1-e111", "segments": [{"type": "text", "text": "أتابع في سورة السجدة، في الصفحة التي تضم الآيات من 12 إلى 20. السورة مكية، وبحسب فهمي فإن الآيات من 16 إلى 20 مدنية، والله أعلم. هذه الصفحة تتابع بيان أن الناس مبعوثون ومحاسبون على أعمالهم، وترد على إنكار الكافرين للبعث بذكر تفاصيل الموت ولقاء الرب وطلب الرجوع إلى الدنيا ليعملوا صالحاً. المشكلة أن الإنسان عند آخر لحظة يقول بمعنى: رب ارجعني لأعمل صالحاً [23:99-100]. وأتذكر معنى آية لا أستحضر نصها الآن، أن الإنسان لو رُدّ إلى الدنيا لتابع ضلاله. تبدأ الصورة بـ"}, {"type": "q", "fragment": "وَلَوْ", "surah": 32, "ayah": 12, "ayah_end": null}, {"type": "text", "text": "، والإنسان هنا أجرم في حق نفسه. ولو شاء الله لهدى الناس جميعاً، فما اختلف منهم أحد، لكن حق القول منه أن تمتلئ جهنم ممن اختار العصيان بعد التكليف، فيخلدون فيها منسيين بسبب تكذيبهم ونسيانهم. أما المؤمنون فتظهر صفاتهم: يسجدون، ويسبحون بحمد"}, {"type": "q", "fragment": "وَهُمْ لَا يَسْتَكْبِرُونَ", "surah": 32, "ayah": 15, "ayah_end": null}, {"type": "q", "fragment": "يَدْعُونَ رَبَّهُمْ خَوْفًا وَطَمَعًا", "surah": 32, "ayah": 16, "ayah_end": null}, {"type": "text", "text": "وينفقون. سبحان الله، أرى هنا بعداً شاقولياً وأفقياً؛ يدعون ربهم إلى الأعلى، إلى خالقنا، خوفاً وطمعاً، وينفقون تجاه البشر. والإنفاق قد يكون بالصدقة، وقد يكون بالكلمة الطيبة، وقد يكون بالعلم، وقد يكون بأي شيء يستطيع الإنسان أن يقوم به. ثم لا يعلم أحد عظم ما أخفى الله لهم من النعيم وقرة الأعين [32:17]. للمؤمنين"}, {"type": "q", "fragment": "جَنَّاتُ الْمَأْوَىٰ نُزُلًا", "surah": 32, "ayah": 19, "ayah_end": null}, {"type": "text", "text": "وأما الذين فسقوا فمأواهم النار؛"}, {"type": "q", "fragment": "كُلَّمَا أَرَادُوا أَنْ يَخْرُجُوا", "surah": 32, "ayah": 20, "ayah_end": null}, {"type": "text", "text": "منها أعيدوا فيها، ويقال لهم تقريعاً وتوبيخاً: ذوقوا عذاب النار الذي كنتم به تكذبون [32:20]. كذبتم ونسيتم، فيأتي يوم القيامة والعياذ بالله: نُسيتم، وذقتم عذاب النار الذي كنتم تكذبون به. وفي الدنيا يذيقهم الله العذاب لعلهم يرجعون، فيتدبرون آياته قبل أن يأتي يوم لا رجوع فيه. وأتوقف سريعاً عند"}, {"type": "q", "fragment": "وَلَوْ تَرَىٰ إِذِ الْمُجْرِمُونَ نَاكِسُو رُءُوسِهِمْ", "surah": 32, "ayah": 12, "ayah_end": null}, {"type": "text", "text": ". أتخيل إنساناً سارقاً أو قاتلاً تقبض عليه الشرطة والناس ينظرون إليه؛ يكون مذلولاً، ناكس الرأس، ذاهباً إلى التحقيق أو المحكمة. فكيف إذا كان ناكس رأسه عند ربه؟ ثم يقولون:"}, {"type": "q", "fragment": "رَبَّنَا أَبْصَرْنَا وَسَمِعْنَا", "surah": 32, "ayah": 12, "ayah_end": null}, {"type": "text", "text": ". لفتني أن البصر جاء قبل السمع؛ كأن كل شيء صار أمامهم واضحاً، شاهدوا وسمعوا. والتوجيه العملي لي أن أعمل صالحاً قبل أن أتمنى العمل ولا أستطيع، وقبل أن أقول: أرجعوني نعمل صالحاً إنا موقنون. والهداية بيد الله عز وجل، فلأجعل لي خبيئة عمل صالح لا يطلع عليها أحد إلا الله، فهناك"}, {"type": "q", "fragment": "فَلَا تَعْلَمُ نَفْسٌ مَا أُخْفِيَ لَهُمْ مِنْ قُرَّةِ أَعْيُنٍ", "surah": 32, "ayah": 17, "ayah_end": null}, {"type": "text", "text": "جزاءً بما كانوا يعملون."}]}}, "t2": null}