{"page": 533, "surahs": [{"num": 55, "ar": "الرحمن", "en": "Ar-Raḥmān"}], "juz": 27, "quran": {"surahs": [{"num": 55, "ar": "سُوْرَةُ الرَّحْمٰنِ", "en": "The Beneficent"}], "surah_ar": "سُوْرَةُ الرَّحْمٰنِ", "surah_en": "The Beneficent", "verses": [{"k": "55:41", "ar": "يُعْرَفُ الْمُجْرِمُونَ بِسِيمَاهُمْ فَيُؤْخَذُ بِالنَّوَاصِي وَالْأَقْدَامِ", "en": "The guilty will be known by their mark and will be seized by their foreheads and their feet", "tafsir": "تَعرِف الملائكة المجرمين بعلاماتهم، فتأخذهم بمقدمة رؤوسهم وبأقدامهم، فترميهم في النار."}, {"k": "55:42", "ar": "فَبِأَيِّ آلَاءِ رَبِّكُمَا تُكَذِّبَانِ", "en": "Which, then, of your Lord’s blessings do you both deny", "tafsir": "فبأي نِعَم ربكما -أيها الثقلان- تكذِّبان؟"}, {"k": "55:43", "ar": "هَٰذِهِ جَهَنَّمُ الَّتِي يُكَذِّبُ بِهَا الْمُجْرِمُونَ", "en": "This is the Hell the guilty deny", "tafsir": "يقال لهؤلاء المجرمين -توبيخًا وتحقيرًا لهم-: هذه جهنم التي يكذِّب بها المجرمون في الدنيا: تارة يُعذَّبون في الجحيم، وتارة يُسقون من الحميم، وهو شراب بلغ منتهى الحرارة، يقطِّع الأمعاء والأحشاء."}, {"k": "55:44", "ar": "يَطُوفُونَ بَيْنَهَا وَبَيْنَ حَمِيمٍ آنٍ", "en": "but they will go round between its flames and scalding water", "tafsir": "يقال لهؤلاء المجرمين -توبيخًا وتحقيرًا لهم-: هذه جهنم التي يكذِّب بها المجرمون في الدنيا: تارة يُعذَّبون في الجحيم، وتارة يُسقون من الحميم، وهو شراب بلغ منتهى الحرارة، يقطِّع الأمعاء والأحشاء."}, {"k": "55:45", "ar": "فَبِأَيِّ آلَاءِ رَبِّكُمَا تُكَذِّبَانِ", "en": "Which, then, of your Lord’s blessings do you both deny", "tafsir": "فبأي نِعَم ربكما -أيها الثقلان- تكذِّبان؟"}, {"k": "55:46", "ar": "وَلِمَنْ خَافَ مَقَامَ رَبِّهِ جَنَّتَانِ", "en": "For those who fear [the time when they will] stand before their Lord there are two gardens", "tafsir": "ولمن اتقى الله من عباده من الإنس والجن، فخاف مقامه بين يديه، فأطاعه، وترك معاصيه، جنتان."}, {"k": "55:47", "ar": "فَبِأَيِّ آلَاءِ رَبِّكُمَا تُكَذِّبَانِ", "en": "Which, then, of your Lord’s blessings do you both deny", "tafsir": "فبأي نِعَم ربكما -أيها الثقلان- تكذِّبان؟"}, {"k": "55:48", "ar": "ذَوَاتَا أَفْنَانٍ", "en": "With shading branches", "tafsir": "الجنتان ذواتا أغصان نضرة من الفواكه والثمار."}, {"k": "55:49", "ar": "فَبِأَيِّ آلَاءِ رَبِّكُمَا تُكَذِّبَانِ", "en": "Which, then, of your Lord’s blessings do you both deny", "tafsir": "فبأي نِعَم ربكما -أيها الثقلان- تكذِّبان؟"}, {"k": "55:50", "ar": "فِيهِمَا عَيْنَانِ تَجْرِيَانِ", "en": "With a pair of flowing springs", "tafsir": "في هاتين الجنتين عينان من الماء تجريان خلالهما."}, {"k": "55:51", "ar": "فَبِأَيِّ آلَاءِ رَبِّكُمَا تُكَذِّبَانِ", "en": "Which, then, of your Lord’s blessings do you both deny", "tafsir": "فبأي نِعَم ربكما -أيها الثقلان- تكذِّبان؟"}, {"k": "55:52", "ar": "فِيهِمَا مِنْ كُلِّ فَاكِهَةٍ زَوْجَانِ", "en": "With every kind of fruit in pairs", "tafsir": "في هاتين الجنتين من كل نوع من الفواكه صنفان."}, {"k": "55:53", "ar": "فَبِأَيِّ آلَاءِ رَبِّكُمَا تُكَذِّبَانِ", "en": "Which, then, of your Lord’s blessings do you both deny", "tafsir": "فبأي نِعَم ربكما -أيها الثقلان- تكذِّبان؟"}, {"k": "55:54", "ar": "مُتَّكِئِينَ عَلَىٰ فُرُشٍ بَطَائِنُهَا مِنْ إِسْتَبْرَقٍ ۚ وَجَنَى الْجَنَّتَيْنِ دَانٍ", "en": "They will sit on couches upholstered with brocade, the fruit of both gardens within easy reach", "tafsir": "وللذين خافوا مقام ربهم جنتان يتنعمون فيهما، متكئين على فرش مبطَّنة من غليظ الديباج، وثمر الجنتين قريب إليهم."}, {"k": "55:55", "ar": "فَبِأَيِّ آلَاءِ رَبِّكُمَا تُكَذِّبَانِ", "en": "Which, then, of your Lord’s blessings do you both deny", "tafsir": "فبأي نِعَم ربكما -أيها الثقلان- تكذِّبان؟"}, {"k": "55:56", "ar": "فِيهِنَّ قَاصِرَاتُ الطَّرْفِ لَمْ يَطْمِثْهُنَّ إِنْسٌ قَبْلَهُمْ وَلَا جَانٌّ", "en": "There will be maidens restraining their glances, untouched beforehand by man or jinn", "tafsir": "في هذه الفرش زوجات قاصرات أبصارهن على أزواجهن، لا ينظرن إلى غيرهم متعلقات بهم، لم يطأهن إنس قبلهم ولا جان."}, {"k": "55:57", "ar": "فَبِأَيِّ آلَاءِ رَبِّكُمَا تُكَذِّبَانِ", "en": "Which, then, of your Lord’s blessings do you both deny", "tafsir": "فبأي نِعَم ربكما -أيها الثقلان- تكذِّبان؟"}, {"k": "55:58", "ar": "كَأَنَّهُنَّ الْيَاقُوتُ وَالْمَرْجَانُ", "en": "Like rubies and brilliant pearls", "tafsir": "كأن هؤلاء الزوجاتِ من الحور الياقوتُ والمَرْجانُ في صفائهن وجمالهن."}, {"k": "55:59", "ar": "فَبِأَيِّ آلَاءِ رَبِّكُمَا تُكَذِّبَانِ", "en": "Which, then, of your Lord’s blessings do you both deny", "tafsir": "فبأي نِعَم ربكما -أيها الثقلان- تكذِّبان؟"}, {"k": "55:60", "ar": "هَلْ جَزَاءُ الْإِحْسَانِ إِلَّا الْإِحْسَانُ", "en": "Shall the reward of good be anything but good", "tafsir": "هل جزاء مَن أحسن بعمله في الدنيا إلا الإحسان إليه بالجنة في الآخرة؟ فبأي نِعَم ربكما -أيها الثقلان- تكذِّبان؟"}, {"k": "55:61", "ar": "فَبِأَيِّ آلَاءِ رَبِّكُمَا تُكَذِّبَانِ", "en": "Which, then, of your Lord’s blessings do you both deny", "tafsir": "هل جزاء مَن أحسن بعمله في الدنيا إلا الإحسان إليه بالجنة في الآخرة؟ فبأي نِعَم ربكما -أيها الثقلان- تكذِّبان؟"}, {"k": "55:62", "ar": "وَمِنْ دُونِهِمَا جَنَّتَانِ", "en": "There are two other gardens below these two", "tafsir": "ومن دون الجنتين السابقتين جنتان أخريان. فبأي نِعَم ربكما -أيها الثقلان- تكذِّبان؟"}, {"k": "55:63", "ar": "فَبِأَيِّ آلَاءِ رَبِّكُمَا تُكَذِّبَانِ", "en": "Which, then, of your Lord’s blessings do you both deny", "tafsir": "ومن دون الجنتين السابقتين جنتان أخريان. فبأي نِعَم ربكما -أيها الثقلان- تكذِّبان؟"}, {"k": "55:64", "ar": "مُدْهَامَّتَانِ", "en": "Both of deepest green", "tafsir": "هاتان الجنتان خضراوان، قد اشتدَّت خضرتهما حتى مالت إلى السواد. فبأي نِعَم ربكما -أيها الثقلان- تكذِّبان؟"}, {"k": "55:65", "ar": "فَبِأَيِّ آلَاءِ رَبِّكُمَا تُكَذِّبَانِ", "en": "Which, then, of your Lord’s blessings do you both deny", "tafsir": "هاتان الجنتان خضراوان، قد اشتدَّت خضرتهما حتى مالت إلى السواد. فبأي نِعَم ربكما -أيها الثقلان- تكذِّبان؟"}, {"k": "55:66", "ar": "فِيهِمَا عَيْنَانِ نَضَّاخَتَانِ", "en": "With a pair of gushing springs", "tafsir": "فيهما عينان فوَّارتان بالماء لا تنقطعان. فبأي نِعَم ربكما -أيها الثقلان- تكذِّبان؟"}, {"k": "55:67", "ar": "فَبِأَيِّ آلَاءِ رَبِّكُمَا تُكَذِّبَانِ", "en": "Which, then, of your Lord’s blessings do you both deny", "tafsir": "فيهما عينان فوَّارتان بالماء لا تنقطعان. فبأي نِعَم ربكما -أيها الثقلان- تكذِّبان؟"}], "source": {"arabic": "Tanzil quran-simple (diacritised)", "translation": "Abdel Haleem", "tafsir": "التفسير الميسر / Tafsir al-Muyassar", "layout": "Madani 604-page mushaf", "verified": "word-checked against quran.ai (MCP)"}}, "quran_com": "https://quran.com/page/533", "t1": {"episode": "T1-e141", "date": "2023-09-01", "session_number": 141, "youtube_id": "1Qzmd_PdWH4", "start_s": 2158, "end_s": 2851, "start": "35:58", "end": "47:31", "presenter": "عبد الكريم اقزيز", "unnamed": false, "voice_code": "Scarlet Raven", "confidence": "high", "text": "بسم الله الرحمن الرحيم الحمد لله رب العالمين أفضل الصلاة والسلام على سيدنا محمد وعلى آله وصحبه أجمعا نكمل في هذا المشهد الذي يقارن ما بين صورتين صورة أهل الشقاء والعذاب وصورة أهل النعيم سبحان الله في القرآن نرى كثيرا هذه المقارنة ما بين أهل الشقاء وما بين أهل النعيم فعندما بدأت الصفحة السابقة بوصف هؤلاء المجرمين الآن تنتقل إلى الصفحة التالية الصفحة 533 إلى توصيف العذاب الذي ينتظر هؤلاء المجرمين ومن ثم تقارن ما بين هذه الصورة صورة الشقاء والألم إلى صورة النعيم والسعادة التي سيتنعم بها أهل الجنة وهذه المقارنة دائما تكون فيها تفصيل وتفصيل أحيانا مادي وحسي ومعنوي وهذا التفصيل كأن القرآن يريد أن يرسم صورة تقرب للأذهان ما هو بعيد وتجسم للإنسان ما هو متخير وبالتالي التوصيف أحيانا في هذه الصورة وفي غيرها عندما يتحدث القرآن عن أهل النار يتحدث أحيانا بالتفاصيل كيف أن جلودهم تتغير ويسيل منهم كذا وهذه الشجرة الزقوم وغيرها أحيانا يتساءل الإنسان لماذا كل هذا التوصيف وعندما قرأت هذه الصفحة حاولت أن أفكر لماذا كل هذا التصوير الأحيانا الحسن وهو فعليا لكي يساعدني أن أتخيل هذه الصورة التي هي في عالم الغيب التي هي لا يمكن لي أن أتخيلها بالتجريب والمشاهدة وبالتالي لابد من رسم تفاصيل تساعدني على التخيل ولذلك تأتي الآيات هنا هذه جهنم التي يكذب بها المجرمون هذه هي النار التي كذب بها المجرمون عندما رويت لهم هذه الآيات وعندما قرأوها كانوا يستهزئون أن هذا لا يمكن أن يكون حقيقيا سبحان الله تذكرت أحد الفيديوهات التي بعثها لي أحد الأداريين عندما كان هناك مثل فيديو كليب مختصر يستهزئ بعذاب أهل النار ويعني كأنه كرتوني ويقول أن الأهل النار يتلظون بجهنم وأهل النعيم الجنة يتنعمون وهذا التكذيب والاستهزاء سوف يرون نتيجته لا محالة عندما يكون المؤمنون على سرر متقابلين وأما المجرمون فهم يجنوا جزاء ما كذبوا به يطوفون بينها وبين حميم آن تخيل هذا المشهد يطوفون بين نار ملتهبة وبين حميم وهو السائل الذي يتلي آن أي أنه نضج يعني نفس عندما نقول غير ناظرين إناه بمعنى عندما نقول إناه فإنه نضج واقترب إلى الاكتمال فبالتالي هذا السائل الذي يغلي ويكتمل غليانه بشكل كامل فتخيل هذا المشهد بين نار وبين حميم سائل يجري وبين دخان وبين مشاعر فعليا تتقطع لها القلوب المؤمنة الذين يخافون عذاب ربهم إن عذابها كان غرامة أو لا إن المؤمنون الذين تجسدوا هذه الصورة المتخيلة وخافوا منها يقينا بأن الله قادر على كل شيء فبأي آلاء ربكما يتكذبان ومن ثم تنتقل الصورة إلى الطرف المقابل تماما إلى النقيب يعني بعيد عن كل هذا العذاب هناك صورة مختلفة تماما لمن هذه الصورة لمن خاف مقام ربه ماذا لديه الذي ينتحل بمرتبة التقوى لديه جنتان لديها أفنان الأفنان هي الألوان المتعددة أو نقول الأغصان ذات فنن فبالتالي لها ألوان متعددة وأشكال مختلفة فيها الأنهار فيهما عينان تجريان الأنهار والماء من كل مكان فيها من كل فاكهة زوجان فبالتالي الفاكهة والأكل والشراب وتخيل معي هذه الصورة المتكئين على فرش هناك صرر يتكون عليها وهم إخوة في هذه الجنة رطائنها من استبرق هذا الدباج الغليظ يحمل من فاخر الأنواع من الصرر وجن الجنتين حتى إذا اشتهوا الفاكهة وكأن هذه الثمار تتدل لتقترب منهم لتحقيق ما يشتهون فيهن قاصرات الطرف أيضا الحور العين لأن هذه الصورة الحسية لقاصرات الطرف أي أنها حتى تجتمع بهذه الحور العين الصورة المادية بأن من جمالهن وأيضا الصورة المعنوية قاصرات الطرف هو مخصصة فقط لأزواجهن لا تمتد أعينهن لغير أزواجهن لم يطمثهن إنس قبلهم ولا جان والآيات عندما سبحان الله حضرت هذه الصفحة كنت أريد أن لا أغوص فعليا في شرع الآيات لأنها واضحة في الحقيقة هي تشرع النعيم الحسي وأيضا المعنوي في الجنة لكن يعني بعد هذا الشرع هناك آية تأتي تذكر هل جزاء الإحسان إلا الإحسان يعني هذا الذي في النعيم الذي استحقه أهل الجنة إنما كان جزاء للإحسان الذي قدمه في الدنيا وهذا هو قمة العدل أن تقدمت إحسانا فيعني حاشا لرب العزة ألا يقدم لك إحسانا أكثر كمالا وأكثر تنعما وأيضا بين دونهن جنتان وتتابع الآيات مدهامتان يعني عندما يعني هذه الأشجار تداخلت مع بعضها البعض فتحولت الأشجار الخضراء إلى سوداء من كثرة تداخلها وتشابكها فيهما عينان مضاختان فيهما فاكهة ونخل ورمان وأتى يعني فاكهة ونخل ورمان أتى تفصيل للفاكهة بتخصيص للنخل والرمان وهذا أسلوب مستعمل في القرآن الكريم ولكن يعني أعود ويعني أحاول أن أتفكر بطريقة فهمنا كمسلمين للمتع المادية الحسية في الجنة لأنه هناك الكثير من أصحاب الطرق والمباهي والأديان وحتى النصارى يحاولون أن يفسروا النعمة التنعمة في الجنة بأنه روحي فقط وبالتالي هم ينكرون أحيانا الأكل والشربة والتمتع الجنسي وغيرها وعلى الطرف النقيض ترى بعض المتطرفين يرون في النعم في الجنة هي نعم مادية حسية فقط والطواب أن يكون ما بين ذلك أولا النعم المادية موجودة بنص القرآن وعندما يعني مذهبنا بأننا إذا إذا قرأنا خبرا فإنما نحاول إما أن نتأكد منه بالتجريب والمشاهدة أو أن نتحقق من نقله وأخبار النعيم في الجنة إنما هي أخبار في عالم الغيب وبالتالي لا يمكن لنا أن نتأكد منها في التجريب والمشاهدة فنعتمد على النقل فإذا ذكر القرآن شيئا من هذه المتعة قررناها على ما هي دون تفسير ولا تأويل غير مدعوم بنص من القرآن أو من الحديث الشريف وتأكيد المدع المتعة على المدية والحسية أكدها رسول الله صلى الله عليه وسلم في حديث عن جابر بن عبد الله يقول يأكل أهل الجنة فيها ويشربون ولكن ولا يتغوطون ولا يمتقطون ولا يبولون وتتمت الحديث وهن الشاهد يلهمون التسبيح والحمد كما تلهمون النفس وبالتالي هناك توازن هي ليست متعة مدية مجرد أولا وثانيا هي ليست متعة مدية ولكن تشبه تلك توازي أو تماما نفس تلك المتعة التي نعيشها في الدنيا نتذكر الآية كلما رزقوا من ثمارها رزقا قالوا هذا الذي رزقنا من قبل وأتوا به متشابها أهل التفسير يقولون أنه نعم تشبه الثمار تشبه ثمار أهل الأرض الثمار الدنيا من ناحية الإسم وقد يكون الشكل ولكن المحتوى مختلف وقد تكون هذه المتعة المادية مختلفة في الجنة ولكن نقر بأنها متعة مادية ولذلك الحديث يقول أنهم يأكلون ويشربون ولا يتغوطون وبالتالي قد طهرت هذه النعم من أي شيء قد يعني يجلب لها القذارة أو مرتبة الدنيا ولكن تتمة في الحديث وفيها الشائد يلهمون التسبحة والحمد هناك التوازن ما بين المادة والمعنى ما بين الروح والجسد وبالتالي هذه المتعة التي رسمناها وتخيلناها من هذه الآيات يجب أن نتذكر أن هناك متعة أكبر وهي لذة النظر إلى وجهه الكريم فهي مرحلة الرضا التي يرضى بها أهل الجنة عن ربهم ويرضى عنهم بهذا التوازن المطلق هذه السعادة المطلقة والأبدية عندما نتخيل هذه الصورة هذه الصورة التي ستدفعنا للعمل وتدفعنا عن أننا من الممكن أن نتحمل ما نتحمله في الدنيا مقابل أن نكون في هذه المرحلة ولذلك نتذكر مثلا حديث عمير عبد الحمام عندما كان في غزوة بدر عندما سمع صفة أهل الجنة وأن نعرضها كعرض السماوات والأرض فقال استحقر واصدر النعمة المادية في الدنيا مقابل هذه النعمة فقال ما حملت على قول بخن بخن لا شيء إلا رجاء أن أكون من أهل الجنة فكما نعلم فقاتل حتى قتل الفقارة صلى الله عليه وسلم يعني بشره بأنه من أهل الجنة وبالتالي ما نفهمه وما يجب أن نأخذه من هذه الآيات التي تصفف لنا وتصور لنا الجنة يجب أن يكون هو شحذ الإمام والقدرة على تخيل هذا العالم الضيبي تخيلا متوازنا بين المتاع المادية والمعنوية جزاكم الله خيرا"}, "t2": null}